Workbook
Name CAMPAIGN: marketing_perf!$B$2:$B$381
Name CATEGORY: marketing_perf!$C$2:$C$381
Name MARKETING_HEADERS: marketing_perf!$A$1:$H$1
Name MARKETING_PERF: marketing_perf!$A$1:$H$381
Name UNIQUE_KEYPHRASES: marketing_perf!$A$1:$A$381

Sheet dashboard
C2: Choose Category: | J2: Choose Campaign:
C3: Women | E3: =COUNTIF(CATEGORY,dashboard!$C$3) -> 186 | F3: key phrases | J3: Designer | L3: =COUNTIF(CAMPAIGN,dashboard!$J$3) -> 89 | M3: key phrases
C5: Ad Cost | D5: Signups | E5: Conv | F5: Sales | J5: Ad Cost | K5: Signups | L5: Conv | M5: Sales
C6: =SUMIF(CATEGORY,dashboard!$C$3,marketing_perf!H2:H381) -> 9601.31 | D6: =SUMIF(CATEGORY,dashboard!$C$3,marketing_perf!E2:E381) -> 11481 | E6: =SUMIF(CATEGORY,dashboard!$C$3,marketing_perf!F2:F381) -> 266 | F6: =SUMIF(CATEGORY,dashboard!$C$3,marketing_perf!G2:G381) -> 21289.69 | J6: =SUMIF(CAMPAIGN,dashboard!J$3,marketing_perf!H2:H381) -> 10614.05 | K6: =SUMIF(CAMPAIGN,dashboard!J$3,marketing_perf!E2:E381) -> 8705 | L6: =SUMIF(CAMPAIGN,dashboard!J$3,marketing_perf!F2:F381) -> 224 | M6: =SUMIF(CAMPAIGN,dashboard!J$3,marketing_perf!G2:G381) -> 17506.2

Sheet marketing_perf
A1: Unique Key Phrases | B1: Campaign | C1: Category | D1: Month | E1: Signups | F1: Conv. | G1: Sales | H1: Ad Cost | J1: Trending | K1: Campaign | L1: Sales | M1: Ad Cost
A2: kids clothes | B2: None | C2: Children | D2: 42370 | E2: 2784 | F2: 70 | G2: 4846.35 | H2: 5590.04 | J2: fashion men clothes | K2: =INDEX(MARKETING_PERF,MATCH(J2,UNIQUE_KEYPHRASES,0),2) -> Designer | L2: =INDEX(MARKETING_PERF,MATCH(J2,UNIQUE_KEYPHRASES,0),7) -> 250 | M2: =INDEX(MARKETING_PERF,MATCH(J2,UNIQUE_KEYPHRASES,0),8) -> 13.11 | O2: INDEX of a Row | P2: =INDEX(E2:H2,2) -> 70
A3: discount designer clothing | B3: Designer | C3: General | D3: 42370 | E3: 1222 | F3: 40 | G3: 2709.43 | H3: 3410.27 | J3: ladies pants | K3: =INDEX(MARKETING_PERF,MATCH(J3,UNIQUE_KEYPHRASES,0),2) -> None | L3: =INDEX(MARKETING_PERF,MATCH(J3,UNIQUE_KEYPHRASES,0),7) -> 260 | M3: =INDEX(MARKETING_PERF,MATCH(J3,UNIQUE_KEYPHRASES,0),8) -> 22.6 | O3: INDEX of a Column | P3: =INDEX(H2:H5,3) -> 212.98
A4: the haute look | B4: Designer | C4: Women | D4: 42370 | E4: 410 | F4: 18 | G4: 1574.12 | H4: 212.98 | J4: discount clothing | K4: =INDEX(MARKETING_PERF,MATCH(J4,UNIQUE_KEYPHRASES,0),2) -> Discount | L4: =INDEX(MARKETING_PERF,MATCH(J4,UNIQUE_KEYPHRASES,0),7) -> 966 | M4: =INDEX(MARKETING_PERF,MATCH(J4,UNIQUE_KEYPHRASES,0),8) -> 465.24 | O4: INDEX of an Array | P4: =INDEX(A2:H5,2,3) -> General
A5: cheap designer clothes | B5: Designer | C5: General | D5: 42401 | E5: 1181 | F5: 27 | G5: 1561.77 | H5: 1376.11 | J5: newborn clothing | K5: =INDEX(MARKETING_PERF,MATCH(J5,UNIQUE_KEYPHRASES,0),2) -> None | L5: =INDEX(MARKETING_PERF,MATCH(J5,UNIQUE_KEYPHRASES,0),7) -> 720 | M5: =INDEX(MARKETING_PERF,MATCH(J5,UNIQUE_KEYPHRASES,0),8) -> 11.92 | O5: INDEX of a Reference Error | P5: =INDEX(MARKETING_PERF,4) -> #REF!
A6: haute | B6: Designer | C6: Women | D6: 42430 | E6: 307 | F6: 18 | G6: 1455.89 | H6: 890.43 | J6: cheap designer | K6: =INDEX(MARKETING_PERF,MATCH(J6,UNIQUE_KEYPHRASES,0),2) -> Discount | L6: =INDEX(MARKETING_PERF,MATCH(J6,UNIQUE_KEYPHRASES,0),7) -> 632 | M6: =INDEX(MARKETING_PERF,MATCH(J6,UNIQUE_KEYPHRASES,0),8) -> 159.16 | O6: INDEX of a Reference Array | P6: =INDEX(MARKETING_PERF,4,5) -> 410
A7: designer sale | B7: Discount | C7: General | D7: 42430 | E7: 302 | F7: 14 | G7: 1379.97 | H7: 491.01 | J7: baby boy clothes | K7: =INDEX(MARKETING_PERF,MATCH(J7,UNIQUE_KEYPHRASES,0),2) -> None | L7: =INDEX(MARKETING_PERF,MATCH(J7,UNIQUE_KEYPHRASES,0),7) -> 160.6 | M7: =INDEX(MARKETING_PERF,MATCH(J7,UNIQUE_KEYPHRASES,0),8) -> 111.2 | O7: INDEX of a Reference Row | P7: =INDEX(MARKETING_HEADERS,2) -> Campaign
A8: bags sale | B8: Discount | C8: Women | D8: 42430 | E8: 41 | F8: 5 | G8: 1199.6 | H8: 49.58 | J8: sue wong | K8: =INDEX(MARKETING_PERF,MATCH(J8,UNIQUE_KEYPHRASES,0),2) -> Designer | L8: =INDEX(MARKETING_PERF,MATCH(J8,UNIQUE_KEYPHRASES,0),7) -> 413 | M8: =INDEX(MARKETING_PERF,MATCH(J8,UNIQUE_KEYPHRASES,0),8) -> 67
A9: gilt | B9: Competition | C9: General | D9: 42370 | E9: 77 | F9: 11 | G9: 1171.27 | H9: 124.84 | J9: luxury bedding | K9: =INDEX(MARKETING_PERF,MATCH(J9,UNIQUE_KEYPHRASES,0),2) -> Designer | L9: =INDEX(MARKETING_PERF,MATCH(J9,UNIQUE_KEYPHRASES,0),7) -> 258 | M9: =INDEX(MARKETING_PERF,MATCH(J9,UNIQUE_KEYPHRASES,0),8) -> 135.78 | O9: MATCH in a Column | P9: =MATCH("cheap designer clothes",A2:A9,0) -> 4
A10: haute couture | B10: Designer | C10: Women | D10: 42401 | E10: 206 | F10: 16 | G10: 1056.38 | H10: 153.42 | J10: men's coats | K10: =INDEX(MARKETING_PERF,MATCH(J10,UNIQUE_KEYPHRASES,0),2) -> None | L10: =INDEX(MARKETING_PERF,MATCH(J10,UNIQUE_KEYPHRASES,0),7) -> 0 | M10: =INDEX(MARKETING_PERF,MATCH(J10,UNIQUE_KEYPHRASES,0),8) -> 5.02 | O10: MATCH in a Row | P10: =MATCH("Signups",MARKETING_HEADERS,0) -> 5
A11: discount clothing | B11: Discount | C11: General | D11: 42370 | E11: 312 | F11: 11 | G11: 966 | H11: 465.24 | J11: diaper bags | K11: =INDEX(MARKETING_PERF,MATCH(J11,UNIQUE_KEYPHRASES,0),2) -> None | L11: =INDEX(MARKETING_PERF,MATCH(J11,UNIQUE_KEYPHRASES,0),7) -> 467.83 | M11: =INDEX(MARKETING_PERF,MATCH(J11,UNIQUE_KEYPHRASES,0),8) -> 295.19
A12: bedding | B12: Designer | C12: Home | D12: 42430 | E12: 132 | F12: 4 | G12: 875 | H12: 65.65 | O12: Key Phrase to Lookup | P12: diaper bag
A13: cheap sherri hill dresses | B13: Discount | C13: Women | D13: 42401 | E13: 481 | F13: 5 | G13: 822 | H13: 270.4 | O13: Metric to lookup | P13: Sales
A14: clothing discount | B14: Discount | C14: Women | D14: 42370 | E14: 636 | F14: 15 | G14: 800.19 | H14: 138.76
A15: newborn clothing | B15: None | C15: Baby | D15: 42370 | E15: 11 | F15: 1 | G15: 720 | H15: 11.92 | O15: VLOOKUP lookup Sales | P15: =VLOOKUP(P12,MARKETING_PERF,7,0) -> 709.9
A16: discount burberry | B16: Discount | C16: Women | D16: 42430 | E16: 306 | F16: 9 | G16: 717.61 | H16: 403.78 | O16: MATCH + INDEX lookup | P16: =INDEX(MARKETING_PERF,MATCH(P12,UNIQUE_KEYPHRASES,0),MATCH(P13,MARKETING_HEADERS,0)) -> 709.9
A17: diaper bag | B17: None | C17: Baby | D17: 42370 | E17: 429 | F17: 8 | G17: 709.9 | H17: 671.8
A18: handbags sale | B18: Discount | C18: Women | D18: 42401 | E18: 69 | F18: 3 | G18: 709.49 | H18: 115.73
A19: ruelala | B19: Competition | C19: General | D19: 42430 | E19: 36 | F19: 8 | G19: 697.48 | H19: 57.21
A20: cheap designer | B20: Discount | C20: General | D20: 42401 | E20: 125 | F20: 6 | G20: 632 | H20: 159.16
A21: designer +handbags | B21: Designer | C21: Women | D21: 42401 | E21: 785 | F21: 10 | G21: 591.6 | H21: 233.84
A22: dooney | B22: Designer | C22: Women | D22: 42430 | E22: 53 | F22: 2 | G22: 487 | H22: 21.2
A23: clothes sale | B23: Discount | C23: General | D23: 42401 | E23: 113 | F23: 4 | G23: 484 | H23: 116.44
A24: handbags | B24: None | C24: Women | D24: 42401 | E24: 83 | F24: 2 | G24: 482.7 | H24: 64.5
A25: clothing online | B25: None | C25: General | D25: 42430 | E25: 84 | F25: 4 | G25: 470.59 | H25: 57.3
A26: diaper bags | B26: None | C26: Baby | D26: 42370 | E26: 270 | F26: 6 | G26: 467.83 | H26: 295.19
A27: beyond the rack | B27: Competition | C27: General | D27: 42430 | E27: 51 | F27: 2 | G27: 458 | H27: 89.58
A28: designer baby diaper bags | B28: None | C28: Baby | D28: 42401 | E28: 28 | F28: 2 | G28: 435 | H28: 49.76
... A381: womens wholesale shoes | B381: Discount | C381: Women | D381: 42370 | E381: 12 | F381: 0 | G381: 0 | H381: 10.28

Sheet signups
C1: Number of User Signups
C2: Category
C3: Baby | D3: Children | E3: General | F3: Home | G3: Men | H3: Other | I3: Women | J3: Total | L3: Category | M3: Discount | N3: Total | O3: % Signups from Discount
A4: Campaigns | B4: Competition | E4: 416 | H4: 321 | J4: 737 | L4: Baby | M4: =HLOOKUP(L4,$B$3:$J$9,4,FALSE) -> 0 | N4: =HLOOKUP(L4,$B$3:$J$9,7,FALSE) -> 2772 | O4: =M4/N4 -> 0
B5: Designer | D5: 54 | E5: 2987 | F5: 405 | G5: 136 | I5: 5123 | J5: 8705 | L5: Children | M5: =HLOOKUP(L5,$B$3:$J$9,4,FALSE) -> 15 | N5: =HLOOKUP(L5,$B$3:$J$9,7,FALSE) -> 5262 | O5: =M5/N5 -> 0.0028506271
B6: Discount | D6: 15 | E6: 2036 | G6: 110 | I6: 3624 | J6: 5785 | L6: Men | M6: =HLOOKUP(L6,$B$3:$J$9,4,FALSE) -> 110 | N6: =HLOOKUP(L6,$B$3:$J$9,7,FALSE) -> 324 | O6: =M6/N6 -> 0.33950617
B7: Event | D7: 86 | I7: 13 | J7: 99 | L7: Women | M7: =HLOOKUP(L7,$B$3:$J$9,4,FALSE) -> 3624 | N7: =HLOOKUP(L7,$B$3:$J$9,7,FALSE) -> 11481 | O7: =M7/N7 -> 0.31565195
B8: None | C8: 2772 | D8: 5107 | E8: 288 | F8: 151 | G8: 78 | I8: 2721 | J8: 11117 | L8: Home | M8: =HLOOKUP(L8,$B$3:$J$9,4,FALSE) -> 0 | N8: =HLOOKUP(L8,$B$3:$J$9,7,FALSE) -> 556 | O8: =M8/N8 -> 0
B9: Total | C9: 2772 | D9: 5262 | E9: 5727 | F9: 556 | G9: 324 | H9: 321 | I9: 11481 | J9: 26443 | L9: General | M9: =HLOOKUP(L9,$B$3:$J$9,4,FALSE) -> 2036 | N9: =HLOOKUP(L9,$B$3:$J$9,7,FALSE) -> 5727 | O9: =M9/N9 -> 0.35550899
L10: Other | M10: =HLOOKUP(L10,$B$3:$J$9,4,FALSE) -> 0 | N10: =HLOOKUP(L10,$B$3:$J$9,7,FALSE) -> 321 | O10: =M10/N10 -> 0

Sheet misc
A1: Unique Category | C1: Unique Campaign
A2: Baby | C2: Designer
A3: Children | C3: Competition
A4: General | C4: Discount
A5: Home | C5: Event
A6: Men | C6: None
A7: Women
A8: Other
