Workbook
Name CAMPAIGN: marketing_perf!$B$2:$B$381
Name CATEGORY: marketing_perf!$C$2:$C$381
Name MARKETING_HEADERS: marketing_perf!$A$1:$H$1
Name MARKETING_PERF: marketing_perf!$A$1:$L$381
Name UNIQUE_KEYPHRASES: marketing_perf!$A$1:$A$381

Sheet dashboard
C2: Choose Category: | J2: Filter on:
C3: Women | E3: =COUNTIF(CATEGORY,dashboard!$C$3) -> 186 | F3: key phrases | J3: Category | K3: Campaign | L3: Sales | M3: Signup Cost Cat
C5: Ad Cost | D5: Signups | E5: Conv | F5: Sales
C6: =SUMIF(CATEGORY,dashboard!$C$3,marketing_perf!H2:H381) -> 9601.31 | D6: =SUMIF(CATEGORY,dashboard!$C$3,marketing_perf!E2:E381) -> 11481 | E6: =SUMIF(CATEGORY,dashboard!$C$3,marketing_perf!F2:F381) -> 266 | F6: =SUMIF(CATEGORY,dashboard!$C$3,marketing_perf!G2:G381) -> 21289.69 | J6: =DCOUNTA(MARKETING_PERF,"Unique Key Phrases",J3:$M$4) -> 380 | K6: key phrases
J9: Ad Cost | K9: Signups | L9: Conv. | M9: Sales
J10: =DSUM(MARKETING_PERF,J9,$J$3:$M$4) -> 31130.84 | K10: =DSUM(MARKETING_PERF,K9,$J$3:$M$4) -> 26443 | L10: =DSUM(MARKETING_PERF,L9,$J$3:$M$4) -> 676 | M10: =DSUM(MARKETING_PERF,M9,$J$3:$M$4) -> 52930.62
K13: Cost / Signup | L13: Sales / Conv | M13: Sales
J14: Best | K14: =DMIN(MARKETING_PERF,K$13,$J$3:$M$4) -> 0.10777778 | L14: =DMAX(MARKETING_PERF,L$13,$J$3:$M$4) -> 720 | M14: =DMAX(MARKETING_PERF,M$13,$J$3:$M$4) -> 4846.35
J15: Worst | K15: =DMAX(MARKETING_PERF,$K$13,$J$3:$M$4) -> 7.49 | L15: =DMIN(MARKETING_PERF,L$13,$J$3:$M$4) -> 5.99 | M15: =DMIN(MARKETING_PERF,M$13,$J$3:$M$4) -> 0

Sheet marketing_perf
A1: Unique Key Phrases | B1: Campaign | C1: Category | D1: Month | E1: Signups | F1: Conv. | G1: Sales | H1: Ad Cost | I1: Cost / Signup | J1: Signup Cost Cat | K1: Sales / Conv | L1: Avg Sales Cat
A2: kids clothes | B2: None | C2: Children | D2: 42370 | E2: 2784 | F2: 70 | G2: 4846.35 | H2: 5590.04 | I2: =IF(E2>0,H2/E2,"") -> 2.0079167 | J2: =IF(ISNUMBER(I2),IF(I2<=0.5,"Low",IF(I2<=1.5,"Medium","High")),"Untested") -> High | K2: =IF(G2>0,G2/F2,"") -> 69.233571 | L2: =IF(ISNUMBER(K2),IF(K2<=75,"Low",IF(K2<=200,"Medium","High")),"Untested") -> Low
A3: discount designer clothing | B3: Designer | C3: General | D3: 42370 | E3: 1222 | F3: 40 | G3: 2709.43 | H3: 3410.27 | I3: =IF(E3>0,H3/E3,"") -> 2.7907283 | J3: =IF(ISNUMBER(I3),IF(I3<=0.5,"Low",IF(I3<=1.5,"Medium","High")),"Untested") -> High | K3: =IF(G3>0,G3/F3,"") -> 67.73575 | L3: =IF(ISNUMBER(K3),IF(K3<=75,"Low",IF(K3<=200,"Medium","High")),"Untested") -> Low
A4: the haute look | B4: Designer | C4: Women | D4: 42370 | E4: 410 | F4: 18 | G4: 1574.12 | H4: 212.98 | I4: =IF(E4>0,H4/E4,"") -> 0.51946341 | J4: =IF(ISNUMBER(I4),IF(I4<=0.5,"Low",IF(I4<=1.5,"Medium","High")),"Untested") -> Medium | K4: =IF(G4>0,G4/F4,"") -> 87.451111 | L4: =IF(ISNUMBER(K4),IF(K4<=75,"Low",IF(K4<=200,"Medium","High")),"Untested") -> Medium
A5: cheap designer clothes | B5: Designer | C5: General | D5: 42401 | E5: 1181 | F5: 27 | G5: 1561.77 | H5: 1376.11 | I5: =IF(E5>0,H5/E5,"") -> 1.1652075 | J5: =IF(ISNUMBER(I5),IF(I5<=0.5,"Low",IF(I5<=1.5,"Medium","High")),"Untested") -> Medium | K5: =IF(G5>0,G5/F5,"") -> 57.843333 | L5: =IF(ISNUMBER(K5),IF(K5<=75,"Low",IF(K5<=200,"Medium","High")),"Untested") -> Low
A6: haute | B6: Designer | C6: Women | D6: 42430 | E6: 307 | F6: 18 | G6: 1455.89 | H6: 890.43 | I6: =IF(E6>0,H6/E6,"") -> 2.9004235 | J6: =IF(ISNUMBER(I6),IF(I6<=0.5,"Low",IF(I6<=1.5,"Medium","High")),"Untested") -> High | K6: =IF(G6>0,G6/F6,"") -> 80.882778 | L6: =IF(ISNUMBER(K6),IF(K6<=75,"Low",IF(K6<=200,"Medium","High")),"Untested") -> Medium
A7: designer sale | B7: Discount | C7: General | D7: 42430 | E7: 302 | F7: 14 | G7: 1379.97 | H7: 491.01 | I7: =IF(E7>0,H7/E7,"") -> 1.6258609 | J7: =IF(ISNUMBER(I7),IF(I7<=0.5,"Low",IF(I7<=1.5,"Medium","High")),"Untested") -> High | K7: =IF(G7>0,G7/F7,"") -> 98.569286 | L7: =IF(ISNUMBER(K7),IF(K7<=75,"Low",IF(K7<=200,"Medium","High")),"Untested") -> Medium
A8: bags sale | B8: Discount | C8: Women | D8: 42430 | E8: 41 | F8: 5 | G8: 1199.6 | H8: 49.58 | I8: =IF(E8>0,H8/E8,"") -> 1.2092683 | J8: =IF(ISNUMBER(I8),IF(I8<=0.5,"Low",IF(I8<=1.5,"Medium","High")),"Untested") -> Medium | K8: =IF(G8>0,G8/F8,"") -> 239.92 | L8: =IF(ISNUMBER(K8),IF(K8<=75,"Low",IF(K8<=200,"Medium","High")),"Untested") -> High
A9: gilt | B9: Competition | C9: General | D9: 42370 | E9: 77 | F9: 11 | G9: 1171.27 | H9: 124.84 | I9: =IF(E9>0,H9/E9,"") -> 1.6212987 | J9: =IF(ISNUMBER(I9),IF(I9<=0.5,"Low",IF(I9<=1.5,"Medium","High")),"Untested") -> High | K9: =IF(G9>0,G9/F9,"") -> 106.47909 | L9: =IF(ISNUMBER(K9),IF(K9<=75,"Low",IF(K9<=200,"Medium","High")),"Untested") -> Medium
A10: haute couture | B10: Designer | C10: Women | D10: 42401 | E10: 206 | F10: 16 | G10: 1056.38 | H10: 153.42 | I10: =IF(E10>0,H10/E10,"") -> 0.74475728 | J10: =IF(ISNUMBER(I10),IF(I10<=0.5,"Low",IF(I10<=1.5,"Medium","High")),"Untested") -> Medium | K10: =IF(G10>0,G10/F10,"") -> 66.02375 | L10: =IF(ISNUMBER(K10),IF(K10<=75,"Low",IF(K10<=200,"Medium","High")),"Untested") -> Low
A11: discount clothing | B11: Discount | C11: General | D11: 42370 | E11: 312 | F11: 11 | G11: 966 | H11: 465.24 | I11: =IF(E11>0,H11/E11,"") -> 1.4911538 | J11: =IF(ISNUMBER(I11),IF(I11<=0.5,"Low",IF(I11<=1.5,"Medium","High")),"Untested") -> Medium | K11: =IF(G11>0,G11/F11,"") -> 87.818182 | L11: =IF(ISNUMBER(K11),IF(K11<=75,"Low",IF(K11<=200,"Medium","High")),"Untested") -> Medium
A12: bedding | B12: Designer | C12: Home | D12: 42430 | E12: 132 | F12: 4 | G12: 875 | H12: 65.65 | I12: =IF(E12>0,H12/E12,"") -> 0.49734848 | J12: =IF(ISNUMBER(I12),IF(I12<=0.5,"Low",IF(I12<=1.5,"Medium","High")),"Untested") -> Low | K12: =IF(G12>0,G12/F12,"") -> 218.75 | L12: =IF(ISNUMBER(K12),IF(K12<=75,"Low",IF(K12<=200,"Medium","High")),"Untested") -> High
A13: cheap sherri hill dresses | B13: Discount | C13: Women | D13: 42401 | E13: 481 | F13: 5 | G13: 822 | H13: 270.4 | I13: =IF(E13>0,H13/E13,"") -> 0.56216216 | J13: =IF(ISNUMBER(I13),IF(I13<=0.5,"Low",IF(I13<=1.5,"Medium","High")),"Untested") -> Medium | K13: =IF(G13>0,G13/F13,"") -> 164.4 | L13: =IF(ISNUMBER(K13),IF(K13<=75,"Low",IF(K13<=200,"Medium","High")),"Untested") -> Medium
... A381: womens wholesale shoes | B381: Discount | C381: Women | D381: 42370 | E381: 12 | F381: 0 | G381: 0 | H381: 10.28 | I381: =IF(E381>0,H381/E381,"") -> 0.85666667 | J381: =IF(ISNUMBER(I381),IF(I381<=0.5,"Low",IF(I381<=1.5,"Medium","High")),"Untested") -> Medium | K381: =IF(G381>0,G381/F381,"") | L381: =IF(ISNUMBER(K381),IF(K381<=75,"Low",IF(K381<=200,"Medium","High")),"Untested") -> Untested

Sheet signups
C1: Number of User Signups
C2: Category
C3: Baby | D3: Children | E3: General | F3: Home | G3: Men | H3: Other | I3: Women | J3: Total | L3: Category | M3: Discount | N3: Total | O3: % Signups from Discount
A4: Campaigns | B4: Competition | E4: 416 | H4: 321 | J4: 737 | L4: Baby | M4: =HLOOKUP(L4,$B$3:$J$9,4,FALSE) -> 0 | N4: =HLOOKUP(L4,$B$3:$J$9,7,FALSE) -> 2772 | O4: =M4/N4 -> 0
B5: Designer | D5: 54 | E5: 2987 | F5: 405 | G5: 136 | I5: 5123 | J5: 8705 | L5: Children | M5: =HLOOKUP(L5,$B$3:$J$9,4,FALSE) -> 15 | N5: =HLOOKUP(L5,$B$3:$J$9,7,FALSE) -> 5262 | O5: =M5/N5 -> 0.0028506271
B6: Discount | D6: 15 | E6: 2036 | G6: 110 | I6: 3624 | J6: 5785 | L6: Men | M6: =HLOOKUP(L6,$B$3:$J$9,4,FALSE) -> 110 | N6: =HLOOKUP(L6,$B$3:$J$9,7,FALSE) -> 324 | O6: =M6/N6 -> 0.33950617
B7: Event | D7: 86 | I7: 13 | J7: 99 | L7: Women | M7: =HLOOKUP(L7,$B$3:$J$9,4,FALSE) -> 3624 | N7: =HLOOKUP(L7,$B$3:$J$9,7,FALSE) -> 11481 | O7: =M7/N7 -> 0.31565195
B8: None | C8: 2772 | D8: 5107 | E8: 288 | F8: 151 | G8: 78 | I8: 2721 | J8: 11117 | L8: Home | M8: =HLOOKUP(L8,$B$3:$J$9,4,FALSE) -> 0 | N8: =HLOOKUP(L8,$B$3:$J$9,7,FALSE) -> 556 | O8: =M8/N8 -> 0
B9: Total | C9: 2772 | D9: 5262 | E9: 5727 | F9: 556 | G9: 324 | H9: 321 | I9: 11481 | J9: 26443 | L9: General | M9: =HLOOKUP(L9,$B$3:$J$9,4,FALSE) -> 2036 | N9: =HLOOKUP(L9,$B$3:$J$9,7,FALSE) -> 5727 | O9: =M9/N9 -> 0.35550899
L10: Other | M10: =HLOOKUP(L10,$B$3:$J$9,4,FALSE) -> 0 | N10: =HLOOKUP(L10,$B$3:$J$9,7,FALSE) -> 321 | O10: =M10/N10 -> 0

Sheet misc
A1: Unique Category | C1: Unique Campaign | E1: Signup Cost Cat
A2: Baby | C2: Designer | E2: High
A3: Children | C3: Competition | E3: Medium
A4: General | C4: Discount | E4: Low
A5: Home | C5: Event | E5: Untested
A6: Men | C6: None
A7: Women
A8: Other
