Workbook

Sheet vgsales
A1: Rank | B1: Name | C1: Platform | D1: Year | E1: Genre | F1: Publisher | G1: NA_Sales | H1: EU_Sales | I1: JP_Sales | J1: Other_Sales | K1: Global_Sales
A2: 1 | B2: Wii Sports | C2: Wii | D2: 2006 | E2: Sports | F2: Nintendo | G2: 41.49 | H2: 29.02 | I2: 3.77 | J2: 8.46 | K2: 82.74
A3: 2 | B3: Super Mario Bros. | C3: NES | D3: 1985 | E3: Platform | F3: Nintendo | G3: 29.08 | H3: 3.58 | I3: 6.81 | J3: 0.77 | K3: 40.24
A4: 3 | B4: Mario Kart Wii | C4: Wii | D4: 2008 | E4: Racing | F4: Nintendo | G4: 15.85 | H4: 12.88 | I4: 3.79 | J4: 3.31 | K4: 35.82
A5: 4 | B5: Wii Sports Resort | C5: Wii | D5: 2009 | E5: Sports | F5: Nintendo | G5: 15.75 | H5: 11.01 | I5: 3.28 | J5: 2.96 | K5: 33
A6: 5 | B6: Pokemon Red/Pokemon Blue | C6: GB | D6: 1996 | E6: Role-Playing | F6: Nintendo | G6: 11.27 | H6: 8.89 | I6: 10.22 | J6: 1 | K6: 31.37
A7: 6 | B7: Tetris | C7: GB | D7: 1989 | E7: Puzzle | F7: Nintendo | G7: 23.2 | H7: 2.26 | I7: 4.22 | J7: 0.58 | K7: 30.26
A8: 7 | B8: New Super Mario Bros. | C8: DS | D8: 2006 | E8: Platform | F8: Nintendo | G8: 11.38 | H8: 9.23 | I8: 6.5 | J8: 2.9 | K8: 30.01
A9: 8 | B9: Wii Play | C9: Wii | D9: 2006 | E9: Misc | F9: Nintendo | G9: 14.03 | H9: 9.2 | I9: 2.93 | J9: 2.85 | K9: 29.02
A10: 9 | B10: New Super Mario Bros. Wii | C10: Wii | D10: 2009 | E10: Platform | F10: Nintendo | G10: 14.59 | H10: 7.06 | I10: 4.7 | J10: 2.26 | K10: 28.62
A11: 10 | B11: Duck Hunt | C11: NES | D11: 1984 | E11: Shooter | F11: Nintendo | G11: 26.93 | H11: 0.63 | I11: 0.28 | J11: 0.47 | K11: 28.31
A12: 11 | B12: Nintendogs | C12: DS | D12: 2005 | E12: Simulation | F12: Nintendo | G12: 9.07 | H12: 11 | I12: 1.93 | J12: 2.75 | K12: 24.76
A13: 12 | B13: Mario Kart DS | C13: DS | D13: 2005 | E13: Racing | F13: Nintendo | G13: 9.81 | H13: 7.57 | I13: 4.13 | J13: 1.92 | K13: 23.42
... A90: 89 | B90: PokÃ©mon Platinum Version | C90: DS | D90: 2008 | E90: Role-Playing | F90: Nintendo | G90: 2.82 | H90: 1.78 | I90: 2.69 | J90: 0.55 | K90: 7.84
A91: 90 | B91: Pac-Man | C91: 2600 | D91: 1982 | E91: Puzzle | F91: Atari | G91: 7.28 | H91: 0.45 | I91: 0 | J91: 0.08 | K91: 7.81
A92: 91 | B92: Grand Theft Auto: Liberty City Stories | C92: PSP | D92: 2005 | E92: Action | F92: Take-Two Interactive | G92: 2.9 | H92: 2.83 | I92: 0.24 | J92: 1.75 | K92: 7.72
A93: 92 | B93: Super Mario Galaxy 2 | C93: Wii | D93: 2010 | E93: Platform | F93: Nintendo | G93: 3.66 | H93: 2.42 | I93: 0.98 | J93: 0.64 | K93: 7.69
A94: 93 | B94: Star Wars Battlefront (2015) | C94: PS4 | D94: 2015 | E94: Shooter | F94: Electronic Arts | G94: 2.93 | H94: 3.29 | I94: 0.22 | J94: 1.23 | K94: 7.67
A95: 94 | B95: Call of Duty: Advanced Warfare | C95: PS4 | D95: 2014 | E95: Shooter | F95: Activision | G95: 2.8 | H95: 3.3 | I95: 0.14 | J95: 1.37 | K95: 7.6
A96: 95 | B96: The Legend of Zelda: Ocarina of Time | C96: N64 | D96: 1998 | E96: Action | F96: Nintendo | G96: 4.1 | H96: 1.89 | I96: 1.45 | J96: 0.16 | K96: 7.6
A97: 96 | B97: Crash Bandicoot 2: Cortex Strikes Back | C97: PS | D97: 1997 | E97: Platform | F97: Sony Computer Entertainment | G97: 3.78 | H97: 2.17 | I97: 1.31 | J97: 0.31 | K97: 7.58
A98: 97 | B98: Super Mario Bros. 2 | C98: NES | D98: 1988 | E98: Platform | F98: Nintendo | G98: 5.39 | H98: 1.18 | I98: 0.7 | J98: 0.19 | K98: 7.46
A99: 98 | B99: Super Smash Bros. for Wii U and 3DS | C99: 3DS | D99: 2014 | E99: Fighting | F99: Nintendo | G99: 3.24 | H99: 1.35 | I99: 2.42 | J99: 0.43 | K99: 7.45
A100: 99 | B100: Call of Duty: World at War | C100: X360 | D100: 2008 | E100: Shooter | F100: Activision | G100: 4.79 | H100: 1.9 | I100: 0 | J100: 0.69 | K100: 7.37
A101: 100 | B101: Battlefield 3 | C101: X360 | D101: 2011 | E101: Shooter | F101: Electronic Arts | G101: 4.46 | H101: 2.13 | I101: 0.06 | J101: 0.69 | K101: 7.34
A102: 101 | B102: The Legend of Zelda: Twilight Princess | C102: Wii | D102: 2006 | E102: Action | F102: Nintendo | G102: 3.83 | H102: 2.19 | I102: 0.6 | J102: 0.7 | K102: 7.31
A103: 102 | B103: Call of Duty: Black Ops 3 | C103: XOne | D103: 2015 | E103: Shooter | F103: Activision | G103: 4.52 | H103: 2.09 | I103: 0.01 | J103: 0.67 | K103: 7.3
... A180: 179 | B180: Tomb Raider II | C180: PS | D180: 1997 | E180: Action | F180: Eidos Interactive | G180: 2.3 | H180: 2.46 | I180: 0.2 | J180: 0.28 | K180: 5.24
A181: 180 | B181: Madden NFL 2004 | C181: PS2 | D181: N/A | E181: Sports | F181: Electronic Arts | G181: 4.26 | H181: 0.26 | I181: 0.01 | J181: 0.71 | K181: 5.23
A182: 181 | B182: Dragon Quest VIII: Journey of the Cursed King | C182: PS2 | D182: 2004 | E182: Role-Playing | F182: Square Enix | G182: 0.65 | H182: 0.75 | I182: 3.61 | J182: 0.2 | K182: 5.21
A183: 182 | B183: Diablo III | C183: PC | D183: 2012 | E183: Role-Playing | F183: Activision | G183: 2.43 | H183: 2.15 | I183: 0 | J183: 0.62 | K183: 5.2
A184: 183 | B184: Super Mario Bros. 3 | C184: GBA | D184: 2003 | E184: Platform | F184: Nintendo | G184: 2.93 | H184: 1.25 | I184: 0.83 | J184: 0.2 | K184: 5.2
A185: 184 | B185: New Super Mario Bros. U | C185: WiiU | D185: 2012 | E185: Platform | F185: Nintendo | G185: 2.32 | H185: 1.3 | I185: 1.27 | J185: 0.31 | K185: 5.19
A186: 185 | B186: Super Mario Land 3: Wario Land | C186: GB | D186: 1994 | E186: Platform | F186: Nintendo | G186: 2.49 | H186: 0.98 | I186: 1.57 | J186: 0.15 | K186: 5.19
A187: 186 | B187: FIFA Soccer 13 | C187: X360 | D187: 2012 | E187: Action | F187: Electronic Arts | G187: 1.08 | H187: 3.48 | I187: 0.03 | J187: 0.58 | K187: 5.18
A188: 187 | B188: The Legend of Zelda: Phantom Hourglass | C188: DS | D188: 2007 | E188: Action | F188: Nintendo | G188: 1.9 | H188: 1.83 | I188: 0.95 | J188: 0.49 | K188: 5.17
A189: 188 | B189: Donkey Kong Country 2: Diddy's Kong Quest | C189: SNES | D189: 1995 | E189: Platform | F189: Nintendo | G189: 2.1 | H189: 0.74 | I189: 2.2 | J189: 0.11 | K189: 5.15
A190: 189 | B190: Tomodachi Life | C190: 3DS | D190: 2013 | E190: Simulation | F190: Nintendo | G190: 0.96 | H190: 2.02 | I190: 1.89 | J190: 0.28 | K190: 5.15
A191: 190 | B191: Mario & Sonic at the Olympic Games | C191: DS | D191: 2008 | E191: Sports | F191: Sega | G191: 1.64 | H191: 2.48 | I191: 0.44 | J191: 0.58 | K191: 5.14
A192: 191 | B192: Medal of Honor: Rising Sun | C192: PS2 | D192: 2003 | E192: Shooter | F192: Electronic Arts | G192: 1.98 | H192: 2.23 | I192: 0.13 | J192: 0.8 | K192: 5.13
A193: 192 | B193: Kirby's Dream Land | C193: GB | D193: 1992 | E193: Platform | F193: Nintendo | G193: 2.71 | H193: 0.61 | I193: 1.7 | J193: 0.11 | K193: 5.13
... A240: 239 | B240: Madden NFL 2005 | C240: PS2 | D240: 2004 | E240: Sports | F240: Electronic Arts | G240: 4.18 | H240: 0.26 | I240: 0.01 | J240: 0.08 | K240: 4.53
A241: 240 | B241: Pitfall! | C241: 2600 | D241: 1981 | E241: Platform | F241: Activision | G241: 4.21 | H241: 0.24 | I241: 0 | J241: 0.05 | K241: 4.5
A242: 241 | B242: Madden NFL 07 | C242: PS2 | D242: 2006 | E242: Sports | F242: Electronic Arts | G242: 3.63 | H242: 0.24 | I242: 0.01 | J242: 0.61 | K242: 4.49
A243: 242 | B243: Spider-Man: The Movie | C243: PS2 | D243: 2002 | E243: Action | F243: Activision | G243: 2.71 | H243: 1.51 | I243: 0.03 | J243: 0.23 | K243: 4.48
A244: 243 | B244: Dragon Quest VII: Warriors of Eden | C244: PS | D244: 2000 | E244: Role-Playing | F244: Enix Corporation | G244: 0.2 | H244: 0.14 | I244: 4.1 | J244: 0.02 | K244: 4.47
A245: 244 | B245: Uncharted: The Nathan Drake Collection | C245: PS4 | D245: 2015 | E245: Action | F245: Sony Computer Entertainment | G245: 1.96 | H245: 1.69 | I245: 0.08 | J245: 0.74 | K245: 4.47
A246: 245 | B246: Call of Duty: Advanced Warfare | C246: PS3 | D246: 2014 | E246: Shooter | F246: Activision | G246: 1.54 | H246: 1.94 | I246: 0.19 | J246: 0.77 | K246: 4.45
A247: 246 | B247: God of War | C247: PS2 | D247: 2005 | E247: Action | F247: Sony Computer Entertainment | G247: 2.71 | H247: 1.29 | I247: 0.02 | J247: 0.43 | K247: 4.45
A248: 247 | B248: Nintendo Land | C248: WiiU | D248: 2012 | E248: Misc | F248: Nintendo | G248: 2.55 | H248: 1.11 | I248: 0.46 | J248: 0.33 | K248: 4.44
A249: 248 | B249: Michael Jackson: The Experience | C249: Wii | D249: 2010 | E249: Misc | F249: Ubisoft | G249: 2.67 | H249: 1.35 | I249: 0.01 | J249: 0.39 | K249: 4.42
A250: 249 | B250: Tony Hawk's Pro Skater 3 | C250: PS2 | D250: 2001 | E250: Sports | F250: Activision | G250: 2.66 | H250: 1.29 | I250: 0.01 | J250: 0.46 | K250: 4.41
A251: 250 | B251: Winning Eleven: Pro Evolution Soccer 2007 | C251: PS2 | D251: 2006 | E251: Sports | F251: Konami Digital Entertainment | G251: 0.1 | H251: 2.39 | I251: 1.05 | J251: 0.86 | K251: 4.39
A252: 251 | B252: The Elder Scrolls IV: Oblivion | C252: X360 | D252: 2006 | E252: Role-Playing | F252: Take-Two Interactive | G252: 2.82 | H252: 1.05 | I252: 0.13 | J252: 0.4 | K252: 4.39
A253: 252 | B253: Zelda II: The Adventure of Link | C253: NES | D253: 1987 | E253: Adventure | F253: Nintendo | G253: 2.19 | H253: 0.5 | I253: 1.61 | J253: 0.08 | K253: 4.38
... A259: 258 | B259: Call of Duty: Advanced Warfare | C259: X360 | D259: 2014 | E259: Shooter | F259: Activision | G259: 2.75 | H259: 1.18 | I259: 0 | J259: 0.37 | K259: 4.31
A260: 259 | B260: Asteroids | C260: 2600 | D260: 1980 | E260: Shooter | F260: Atari | G260: 4 | H260: 0.26 | I260: 0 | J260: 0.05 | K260: 4.31
A261: 260 | B261: Fable II | C261: X360 | D261: 2008 | E261: Role-Playing | F261: Microsoft Game Studios | G261: 2.51 | H261: 1.27 | I261: 0.11 | J261: 0.41 | K261: 4.31
A262: 261 | B262: Halo 5: Guardians | C262: XOne | D262: 2015 | E262: Shooter | F262: Microsoft Game Studios | G262: 2.64 | H262: 1.2 | I262: 0.03 | J262: 0.39 | K262: 4.26
A263: 262 | B263: Super Mario 3D World | C263: WiiU | D263: 2013 | E263: Platform | F263: Nintendo | G263: 2.11 | H263: 1.11 | I263: 0.72 | J263: 0.3 | K263: 4.25
A264: 263 | B264: Batman: Arkham Asylum | C264: PS3 | D264: 2009 | E264: Action | F264: Eidos Interactive | G264: 2.23 | H264: 1.34 | I264: 0.07 | J264: 0.61 | K264: 4.25
A265: 264 | B265: Assassin's Creed: Revelations | C265: PS3 | D265: 2011 | E265: Action | F265: Ubisoft | G265: 1.41 | H265: 2.02 | I265: 0.1 | J265: 0.72 | K265: 4.24
A266: 265 | B266: Namco Museum | C266: GBA | D266: 2001 | E266: Misc | F266: Namco Bandai Games | G266: 3 | H266: 1.11 | I266: 0.05 | J266: 0.07 | K266: 4.24
A267: 266 | B267: Metal Gear Solid 3: Snake Eater | C267: PS2 | D267: 2004 | E267: Action | F267: Konami Digital Entertainment | G267: 1.46 | H267: 0 | I267: 0.83 | J267: 1.93 | K267: 4.23
A268: 267 | B268: Daxter | C268: PSP | D268: 2006 | E268: Platform | F268: Sony Computer Entertainment | G268: 2.45 | H268: 1.02 | I268: 0 | J268: 0.75 | K268: 4.22
A269: 268 | B269: Warcraft II: Tides of Darkness | C269: PC | D269: 1995 | E269: Strategy | F269: Activision | G269: 1.7 | H269: 2.27 | I269: 0 | J269: 0.23 | K269: 4.21
A270: 269 | B270: The Legend of Zelda: Ocarina of Time | C270: 3DS | D270: 2011 | E270: Action | F270: Nintendo | G270: 2.03 | H270: 1.27 | I270: 0.62 | J270: 0.3 | K270: 4.21
A271: 270 | B271: FIFA Soccer 06 | C271: PS2 | D271: 2005 | E271: Sports | F271: Electronic Arts | G271: 0.78 | H271: 2.55 | I271: 0.04 | J271: 0.84 | K271: 4.21
A272: 271 | B272: EyeToy Play | C272: PS2 | D272: 2003 | E272: Misc | F272: Sony Computer Entertainment | G272: 0.88 | H272: 2.3 | I272: 0.2 | J272: 0.83 | K272: 4.2
... A378: 377 | B378: Clubhouse Games | C378: DS | D378: 2006 | E378: Misc | F378: Nintendo | G378: 0.59 | H378: 1.83 | I378: 0.73 | J378: 0.35 | K378: 3.5
A379: 378 | B379: FIFA Soccer 2004 | C379: PS2 | D379: N/A | E379: Sports | F379: Electronic Arts | G379: 0.59 | H379: 2.36 | I379: 0.04 | J379: 0.51 | K379: 3.49
A380: 379 | B380: Star Wars Battlefront (2015) | C380: XOne | D380: 2015 | E380: Shooter | F380: Electronic Arts | G380: 1.94 | H380: 1.22 | I380: 0.02 | J380: 0.31 | K380: 3.49
A381: 380 | B381: Battlefield: Bad Company 2 | C381: X360 | D381: 2010 | E381: Shooter | F381: Electronic Arts | G381: 2.09 | H381: 1.02 | I381: 0.04 | J381: 0.32 | K381: 3.48
A382: 381 | B382: Guitar Hero: On Tour | C382: DS | D382: 2008 | E382: Misc | F382: Activision | G382: 2.11 | H382: 1.01 | I382: 0.01 | J382: 0.35 | K382: 3.48
A383: 382 | B383: Assassin's Creed: Unity | C383: XOne | D383: 2014 | E383: Action | F383: Ubisoft | G383: 2.26 | H383: 0.89 | I383: 0 | J383: 0.3 | K383: 3.46
A384: 383 | B384: Far Cry 3 | C384: PS3 | D384: 2012 | E384: Shooter | F384: Ubisoft | G384: 0.88 | H384: 1.75 | I384: 0.1 | J384: 0.72 | K384: 3.45
A385: 384 | B385: Monster Hunter 4 | C385: 3DS | D385: 2013 | E385: Role-Playing | F385: Capcom | G385: 0 | H385: 0 | I385: 3.44 | J385: 0 | K385: 3.44
A386: 385 | B386: Borderlands | C386: X360 | D386: 2009 | E386: Shooter | F386: Take-Two Interactive | G386: 2.39 | H386: 0.73 | I386: 0.03 | J386: 0.29 | K386: 3.44
A387: 386 | B387: Tekken 4 | C387: PS2 | D387: 2002 | E387: Fighting | F387: Namco Bandai Games | G387: 1.55 | H387: 1.27 | I387: 0.33 | J387: 0.29 | K387: 3.44
A388: 387 | B388: Battlefield 4 | C388: PS4 | D388: 2013 | E388: Shooter | F388: Electronic Arts | G388: 1.34 | H388: 1.54 | I388: 0.17 | J388: 0.38 | K388: 3.43
A389: 388 | B389: LittleBigPlanet 2 | C389: PS3 | D389: 2011 | E389: Platform | F389: Sony Computer Entertainment | G389: 1.82 | H389: 1.07 | I389: 0.06 | J389: 0.47 | K389: 3.42
A390: 389 | B390: Grand Theft Auto 2 | C390: PS | D390: 1998 | E390: Action | F390: Take-Two Interactive | G390: 1.13 | H390: 2.07 | I390: 0 | J390: 0.22 | K390: 3.42
A391: 390 | B391: Final Fantasy III | C391: SNES | D391: 1994 | E391: Role-Playing | F391: SquareSoft | G391: 0.86 | H391: 0 | I391: 2.55 | J391: 0.02 | K391: 3.42
... A432: 431 | B432: Fallout: New Vegas | C432: PS3 | D432: 2010 | E432: Role-Playing | F432: Bethesda Softworks | G432: 1.52 | H432: 1.08 | I432: 0.1 | J432: 0.47 | K432: 3.17
A433: 432 | B433: LEGO Batman: The Videogame | C433: Wii | D433: N/A | E433: Action | F433: Warner Bros. Interactive Entertainment | G433: 1.86 | H433: 1.02 | I433: 0 | J433: 0.29 | K433: 3.17
A434: 433 | B434: Rhythm Heaven | C434: DS | D434: 2008 | E434: Misc | F434: Nintendo | G434: 0.58 | H434: 0.51 | I434: 1.93 | J434: 0.14 | K434: 3.17
A435: 434 | B435: Ace Combat 04: Shattered Skies | C435: PS2 | D435: 2001 | E435: Simulation | F435: Sony Computer Entertainment Europe | G435: 2.06 | H435: 0.56 | I435: 0.38 | J435: 0.17 | K435: 3.17
A436: 435 | B436: Club Penguin: Elite Penguin Force | C436: DS | D436: 2008 | E436: Adventure | F436: Disney Interactive Studios | G436: 1.88 | H436: 0.98 | I436: 0 | J436: 0.3 | K436: 3.16
A437: 436 | B437: Animal Crossing | C437: GC | D437: 2001 | E437: Simulation | F437: Nintendo | G437: 1.92 | H437: 0.16 | I437: 0.99 | J437: 0.09 | K437: 3.15
A438: 437 | B438: LEGO Batman: The Videogame | C438: DS | D438: 2008 | E438: Action | F438: Warner Bros. Interactive Entertainment | G438: 1.79 | H438: 1.06 | I438: 0 | J438: 0.29 | K438: 3.15
A439: 438 | B439: Sonic Rush | C439: DS | D439: 2005 | E439: Platform | F439: Sega | G439: 1.22 | H439: 1.57 | I439: 0.06 | J439: 0.29 | K439: 3.15
A440: 439 | B440: Resident Evil 6 | C440: PS3 | D440: 2012 | E440: Shooter | F440: Capcom | G440: 0.88 | H440: 0.97 | I440: 0.88 | J440: 0.42 | K440: 3.15
A441: 440 | B441: Halo: The Master Chief Collection | C441: XOne | D441: 2014 | E441: Shooter | F441: Microsoft Game Studios | G441: 1.89 | H441: 0.99 | I441: 0.03 | J441: 0.24 | K441: 3.15
A442: 441 | B442: FIFA Soccer 08 | C442: PS2 | D442: 2007 | E442: Sports | F442: Electronic Arts | G442: 0.68 | H442: 0 | I442: 0 | J442: 2.46 | K442: 3.14
A443: 442 | B443: Spider-Man | C443: PS | D443: 2000 | E443: Action | F443: Activision | G443: 1.7 | H443: 1.25 | I443: 0.02 | J443: 0.16 | K443: 3.13
A444: 443 | B444: Need for Speed III: Hot Pursuit | C444: PS | D444: 1998 | E444: Racing | F444: Electronic Arts | G444: 2.14 | H444: 0.86 | I444: 0 | J444: 0.13 | K444: 3.12
A445: 444 | B445: Star Wars Episode I Racer | C445: N64 | D445: 1999 | E445: Racing | F445: Nintendo | G445: 2.31 | H445: 0.62 | I445: 0.14 | J445: 0.04 | K445: 3.12
... A471: 470 | B471: Dragon Ball Z: Budokai Tenkaichi 3 | C471: PS2 | D471: 2007 | E471: Fighting | F471: Atari | G471: 1.15 | H471: 0 | I471: 0.76 | J471: 1.09 | K471: 3
A472: 471 | B472: wwe Smackdown vs. Raw 2006 | C472: PS2 | D472: N/A | E472: Fighting | F472: N/A | G472: 1.57 | H472: 1.02 | I472: 0 | J472: 0.41 | K472: 3
A473: 472 | B473: Middle-Earth: Shadow of Mordor | C473: PS4 | D473: 2014 | E473: Action | F473: Warner Bros. Interactive Entertainment | G473: 1.01 | H473: 1.41 | I473: 0.05 | J473: 0.53 | K473: 2.99
...

Sheet Charts
A1: Platform | B1: Total Global Copies Sold | N1: Genre | O1: Total Global Copies Sold
A2: PS2 | B2: =SUMIF(vgsales!$C$2:$C$16599,A2,vgsales!$K$2:$K$16599) -> 1255.64 | N2: Sports | O2: =SUMIF(vgsales!$E$2:$E$16599,Charts!N2,vgsales!$K$2:$K$16599) -> 1330.93
A3: X360 | B3: =SUMIF(vgsales!$C$2:$C$16599,A3,vgsales!$K$2:$K$16599) -> 979.96 | N3: Platform | O3: =SUMIF(vgsales!$E$2:$E$16599,Charts!N3,vgsales!$K$2:$K$16599) -> 831.37
A4: PS3 | B4: =SUMIF(vgsales!$C$2:$C$16599,A4,vgsales!$K$2:$K$16599) -> 957.84 | N4: Racing | O4: =SUMIF(vgsales!$E$2:$E$16599,Charts!N4,vgsales!$K$2:$K$16599) -> 732.04
A5: Wii | B5: =SUMIF(vgsales!$C$2:$C$16599,A5,vgsales!$K$2:$K$16599) -> 926.71 | N5: Sports | O5: =SUMIF(vgsales!$E$2:$E$16599,Charts!N5,vgsales!$K$2:$K$16599) -> 1330.93
A6: DS | B6: =SUMIF(vgsales!$C$2:$C$16599,A6,vgsales!$K$2:$K$16599) -> 822.49 | N6: Role-Playing | O6: =SUMIF(vgsales!$E$2:$E$16599,Charts!N6,vgsales!$K$2:$K$16599) -> 927.37
A7: PS | B7: =SUMIF(vgsales!$C$2:$C$16599,A7,vgsales!$K$2:$K$16599) -> 730.66 | N7: Puzzle | O7: =SUMIF(vgsales!$E$2:$E$16599,Charts!N7,vgsales!$K$2:$K$16599) -> 244.95
A8: GBA | B8: =SUMIF(vgsales!$C$2:$C$16599,A8,vgsales!$K$2:$K$16599) -> 318.5 | N8: Misc | O8: =SUMIF(vgsales!$E$2:$E$16599,Charts!N8,vgsales!$K$2:$K$16599) -> 809.96
A9: PSP | B9: =SUMIF(vgsales!$C$2:$C$16599,A9,vgsales!$K$2:$K$16599) -> 296.28 | N9: Shooter | O9: =SUMIF(vgsales!$E$2:$E$16599,Charts!N9,vgsales!$K$2:$K$16599) -> 1037.37
A10: PS4 | B10: =SUMIF(vgsales!$C$2:$C$16599,A10,vgsales!$K$2:$K$16599) -> 278.1 | N10: Simulation | O10: =SUMIF(vgsales!$E$2:$E$16599,Charts!N10,vgsales!$K$2:$K$16599) -> 392.2
A11: PC | B11: =SUMIF(vgsales!$C$2:$C$16599,A11,vgsales!$K$2:$K$16599) -> 258.82 | N11: Action | O11: =SUMIF(vgsales!$E$2:$E$16599,Charts!N11,vgsales!$K$2:$K$16599) -> 1751.18
A12: XB | B12: =SUMIF(vgsales!$C$2:$C$16599,A12,vgsales!$K$2:$K$16599) -> 258.26 | N12: Fighting | O12: =SUMIF(vgsales!$E$2:$E$16599,Charts!N12,vgsales!$K$2:$K$16599) -> 448.91
A13: GB | B13: =SUMIF(vgsales!$C$2:$C$16599,A13,vgsales!$K$2:$K$16599) -> 255.45 | N13: Adventure | O13: =SUMIF(vgsales!$E$2:$E$16599,Charts!N13,vgsales!$K$2:$K$16599) -> 239.04
A14: NES | B14: =SUMIF(vgsales!$C$2:$C$16599,A14,vgsales!$K$2:$K$16599) -> 251.07 | N14: Strategy | O14: =SUMIF(vgsales!$E$2:$E$16599,Charts!N14,vgsales!$K$2:$K$16599) -> 175.12
A15: 3DS | B15: =SUMIF(vgsales!$C$2:$C$16599,A15,vgsales!$K$2:$K$16599) -> 247.46
A16: N64 | B16: =SUMIF(vgsales!$C$2:$C$16599,A16,vgsales!$K$2:$K$16599) -> 218.88
A17: SNES | B17: =SUMIF(vgsales!$C$2:$C$16599,A17,vgsales!$K$2:$K$16599) -> 200.05
A18: GC | B18: =SUMIF(vgsales!$C$2:$C$16599,A18,vgsales!$K$2:$K$16599) -> 199.36
A19: XOne | B19: =SUMIF(vgsales!$C$2:$C$16599,A19,vgsales!$K$2:$K$16599) -> 141.06
A20: 2600 | B20: =SUMIF(vgsales!$C$2:$C$16599,A20,vgsales!$K$2:$K$16599) -> 97.08
A21: WiiU | B21: =SUMIF(vgsales!$C$2:$C$16599,A21,vgsales!$K$2:$K$16599) -> 81.86
A22: PSV | B22: =SUMIF(vgsales!$C$2:$C$16599,A22,vgsales!$K$2:$K$16599) -> 61.93
A23: SAT | B23: =SUMIF(vgsales!$C$2:$C$16599,A23,vgsales!$K$2:$K$16599) -> 33.59
A24: GEN | B24: =SUMIF(vgsales!$C$2:$C$16599,A24,vgsales!$K$2:$K$16599) -> 28.36
A25: DC | B25: =SUMIF(vgsales!$C$2:$C$16599,A25,vgsales!$K$2:$K$16599) -> 15.97
A26: SCD | B26: =SUMIF(vgsales!$C$2:$C$16599,A26,vgsales!$K$2:$K$16599) -> 1.87
A27: NG | B27: =SUMIF(vgsales!$C$2:$C$16599,A27,vgsales!$K$2:$K$16599) -> 1.44
A28: WS | B28: =SUMIF(vgsales!$C$2:$C$16599,A28,vgsales!$K$2:$K$16599) -> 1.42
A29: TG16 | B29: =SUMIF(vgsales!$C$2:$C$16599,A29,vgsales!$K$2:$K$16599) -> 0.16
A30: 3DO | B30: =SUMIF(vgsales!$C$2:$C$16599,A30,vgsales!$K$2:$K$16599) -> 0.1
A31: GG | B31: =SUMIF(vgsales!$C$2:$C$16599,A31,vgsales!$K$2:$K$16599) -> 0.04
A32: PCFX | B32: =SUMIF(vgsales!$C$2:$C$16599,A32,vgsales!$K$2:$K$16599) -> 0.03
A36: Year | B36: Total Global Copies Sold
A37: 1980 | B37: =SUMIF(vgsales!$D$2:$D$16599,Charts!A37,vgsales!$K$2:$K$16599) -> 11.38
A38: 1981 | B38: =SUMIF(vgsales!$D$2:$D$16599,Charts!A38,vgsales!$K$2:$K$16599) -> 35.77
A39: 1982 | B39: =SUMIF(vgsales!$D$2:$D$16599,Charts!A39,vgsales!$K$2:$K$16599) -> 28.86
A40: 1983 | B40: =SUMIF(vgsales!$D$2:$D$16599,Charts!A40,vgsales!$K$2:$K$16599) -> 16.79
A41: 1984 | B41: =SUMIF(vgsales!$D$2:$D$16599,Charts!A41,vgsales!$K$2:$K$16599) -> 50.36
A42: 1985 | B42: =SUMIF(vgsales!$D$2:$D$16599,Charts!A42,vgsales!$K$2:$K$16599) -> 53.94
A43: 1986 | B43: =SUMIF(vgsales!$D$2:$D$16599,Charts!A43,vgsales!$K$2:$K$16599) -> 37.07
A44: 1987 | B44: =SUMIF(vgsales!$D$2:$D$16599,Charts!A44,vgsales!$K$2:$K$16599) -> 21.74
A45: 1988 | B45: =SUMIF(vgsales!$D$2:$D$16599,Charts!A45,vgsales!$K$2:$K$16599) -> 47.22
A46: 1989 | B46: =SUMIF(vgsales!$D$2:$D$16599,Charts!A46,vgsales!$K$2:$K$16599) -> 73.45
A47: 1990 | B47: =SUMIF(vgsales!$D$2:$D$16599,Charts!A47,vgsales!$K$2:$K$16599) -> 49.39
A48: 1991 | B48: =SUMIF(vgsales!$D$2:$D$16599,Charts!A48,vgsales!$K$2:$K$16599) -> 32.23
... A73: 2016 | B73: =SUMIF(vgsales!$D$2:$D$16599,Charts!A73,vgsales!$K$2:$K$16599) -> 70.93
