Workbook

Sheet vgsales
A1: Rank | B1: Name | C1: Platform | D1: Year | E1: Genre | F1: Publisher | G1: NA_Sales | H1: EU_Sales | I1: JP_Sales | J1: Other_Sales | K1: Global_Sales | N1: Platform | O1: Total Global Copies Sold
A2: 1 | B2: Wii Sports | C2: Wii | D2: 2006 | E2: Sports | F2: Nintendo | G2: 41.49 | H2: 29.02 | I2: 3.77 | J2: 8.46 | K2: 82.74 | N2: PS2 | O2: =SUMIF($C$2:$C$16599,N2,$K$2:$K$16599) -> 1255.64
A3: 2 | B3: Super Mario Bros. | C3: NES | D3: 1985 | E3: Platform | F3: Nintendo | G3: 29.08 | H3: 3.58 | I3: 6.81 | J3: 0.77 | K3: 40.24 | N3: X360 | O3: =SUMIF($C$2:$C$16599,N3,$K$2:$K$16599) -> 979.96
A4: 3 | B4: Mario Kart Wii | C4: Wii | D4: 2008 | E4: Racing | F4: Nintendo | G4: 15.85 | H4: 12.88 | I4: 3.79 | J4: 3.31 | K4: 35.82 | N4: PS3 | O4: =SUMIF($C$2:$C$16599,N4,$K$2:$K$16599) -> 957.84
A5: 4 | B5: Wii Sports Resort | C5: Wii | D5: 2009 | E5: Sports | F5: Nintendo | G5: 15.75 | H5: 11.01 | I5: 3.28 | J5: 2.96 | K5: 33 | N5: Wii | O5: =SUMIF($C$2:$C$16599,N5,$K$2:$K$16599) -> 926.71
A6: 5 | B6: Pokemon Red/Pokemon Blue | C6: GB | D6: 1996 | E6: Role-Playing | F6: Nintendo | G6: 11.27 | H6: 8.89 | I6: 10.22 | J6: 1 | K6: 31.37 | N6: DS | O6: =SUMIF($C$2:$C$16599,N6,$K$2:$K$16599) -> 822.49
A7: 6 | B7: Tetris | C7: GB | D7: 1989 | E7: Puzzle | F7: Nintendo | G7: 23.2 | H7: 2.26 | I7: 4.22 | J7: 0.58 | K7: 30.26 | N7: PS | O7: =SUMIF($C$2:$C$16599,N7,$K$2:$K$16599) -> 730.66
A8: 7 | B8: New Super Mario Bros. | C8: DS | D8: 2006 | E8: Platform | F8: Nintendo | G8: 11.38 | H8: 9.23 | I8: 6.5 | J8: 2.9 | K8: 30.01 | N8: GBA | O8: =SUMIF($C$2:$C$16599,N8,$K$2:$K$16599) -> 318.5
A9: 8 | B9: Wii Play | C9: Wii | D9: 2006 | E9: Misc | F9: Nintendo | G9: 14.03 | H9: 9.2 | I9: 2.93 | J9: 2.85 | K9: 29.02 | N9: PSP | O9: =SUMIF($C$2:$C$16599,N9,$K$2:$K$16599) -> 296.28
A10: 9 | B10: New Super Mario Bros. Wii | C10: Wii | D10: 2009 | E10: Platform | F10: Nintendo | G10: 14.59 | H10: 7.06 | I10: 4.7 | J10: 2.26 | K10: 28.62 | N10: PS4 | O10: =SUMIF($C$2:$C$16599,N10,$K$2:$K$16599) -> 278.1
A11: 10 | B11: Duck Hunt | C11: NES | D11: 1984 | E11: Shooter | F11: Nintendo | G11: 26.93 | H11: 0.63 | I11: 0.28 | J11: 0.47 | K11: 28.31 | N11: PC | O11: =SUMIF($C$2:$C$16599,N11,$K$2:$K$16599) -> 258.82
A12: 11 | B12: Nintendogs | C12: DS | D12: 2005 | E12: Simulation | F12: Nintendo | G12: 9.07 | H12: 11 | I12: 1.93 | J12: 2.75 | K12: 24.76 | N12: XB | O12: =SUMIF($C$2:$C$16599,N12,$K$2:$K$16599) -> 258.26
A13: 12 | B13: Mario Kart DS | C13: DS | D13: 2005 | E13: Racing | F13: Nintendo | G13: 9.81 | H13: 7.57 | I13: 4.13 | J13: 1.92 | K13: 23.42 | N13: GB | O13: =SUMIF($C$2:$C$16599,N13,$K$2:$K$16599) -> 255.45
... A19: 18 | B19: Grand Theft Auto: San Andreas | C19: PS2 | D19: 2004 | E19: Action | F19: Take-Two Interactive | G19: 9.43 | H19: 0.4 | I19: 0.41 | J19: 10.57 | K19: 20.81 | N19: XOne | O19: =SUMIF($C$2:$C$16599,N19,$K$2:$K$16599) -> 141.06
A20: 19 | B20: Super Mario World | C20: SNES | D20: 1990 | E20: Platform | F20: Nintendo | G20: 12.78 | H20: 3.75 | I20: 3.54 | J20: 0.55 | K20: 20.61 | N20: 2600 | O20: =SUMIF($C$2:$C$16599,N20,$K$2:$K$16599) -> 97.08
A21: 20 | B21: Brain Age: Train Your Brain in Minutes a Day | C21: DS | D21: 2005 | E21: Misc | F21: Nintendo | G21: 4.75 | H21: 9.26 | I21: 4.16 | J21: 2.05 | K21: 20.22 | N21: WiiU | O21: =SUMIF($C$2:$C$16599,N21,$K$2:$K$16599) -> 81.86
A22: 21 | B22: Pokemon Diamond/Pokemon Pearl | C22: DS | D22: 2006 | E22: Role-Playing | F22: Nintendo | G22: 6.42 | H22: 4.52 | I22: 6.04 | J22: 1.37 | K22: 18.36 | N22: PSV | O22: =SUMIF($C$2:$C$16599,N22,$K$2:$K$16599) -> 61.93
A23: 22 | B23: Super Mario Land | C23: GB | D23: 1989 | E23: Platform | F23: Nintendo | G23: 10.83 | H23: 2.71 | I23: 4.18 | J23: 0.42 | K23: 18.14 | N23: SAT | O23: =SUMIF($C$2:$C$16599,N23,$K$2:$K$16599) -> 33.59
A24: 23 | B24: Super Mario Bros. 3 | C24: NES | D24: 1988 | E24: Platform | F24: Nintendo | G24: 9.54 | H24: 3.44 | I24: 3.84 | J24: 0.46 | K24: 17.28 | N24: GEN | O24: =SUMIF($C$2:$C$16599,N24,$K$2:$K$16599) -> 28.36
A25: 24 | B25: Grand Theft Auto V | C25: X360 | D25: 2013 | E25: Action | F25: Take-Two Interactive | G25: 9.63 | H25: 5.31 | I25: 0.06 | J25: 1.38 | K25: 16.38 | N25: DC | O25: =SUMIF($C$2:$C$16599,N25,$K$2:$K$16599) -> 15.97
A26: 25 | B26: Grand Theft Auto: Vice City | C26: PS2 | D26: 2002 | E26: Action | F26: Take-Two Interactive | G26: 8.41 | H26: 5.49 | I26: 0.47 | J26: 1.78 | K26: 16.15 | N26: SCD | O26: =SUMIF($C$2:$C$16599,N26,$K$2:$K$16599) -> 1.87
A27: 26 | B27: Pokemon Ruby/Pokemon Sapphire | C27: GBA | D27: 2002 | E27: Role-Playing | F27: Nintendo | G27: 6.06 | H27: 3.9 | I27: 5.38 | J27: 0.5 | K27: 15.85 | N27: NG | O27: =SUMIF($C$2:$C$16599,N27,$K$2:$K$16599) -> 1.44
A28: 27 | B28: Pokemon Black/Pokemon White | C28: DS | D28: 2010 | E28: Role-Playing | F28: Nintendo | G28: 5.57 | H28: 3.28 | I28: 5.65 | J28: 0.82 | K28: 15.32 | N28: WS | O28: =SUMIF($C$2:$C$16599,N28,$K$2:$K$16599) -> 1.42
A29: 28 | B29: Brain Age 2: More Training in Minutes a Day | C29: DS | D29: 2005 | E29: Puzzle | F29: Nintendo | G29: 3.44 | H29: 5.36 | I29: 5.32 | J29: 1.18 | K29: 15.3 | N29: TG16 | O29: =SUMIF($C$2:$C$16599,N29,$K$2:$K$16599) -> 0.16
A30: 29 | B30: Gran Turismo 3: A-Spec | C30: PS2 | D30: 2001 | E30: Racing | F30: Sony Computer Entertainment | G30: 6.85 | H30: 5.09 | I30: 1.87 | J30: 1.16 | K30: 14.98 | N30: 3DO | O30: =SUMIF($C$2:$C$16599,N30,$K$2:$K$16599) -> 0.1
A31: 30 | B31: Call of Duty: Modern Warfare 3 | C31: X360 | D31: 2011 | E31: Shooter | F31: Activision | G31: 9.03 | H31: 4.28 | I31: 0.13 | J31: 1.32 | K31: 14.76 | N31: GG | O31: =SUMIF($C$2:$C$16599,N31,$K$2:$K$16599) -> 0.04
A32: 31 | B32: PokÃ©mon Yellow: Special Pikachu Edition | C32: GB | D32: 1998 | E32: Role-Playing | F32: Nintendo | G32: 5.89 | H32: 5.04 | I32: 3.12 | J32: 0.59 | K32: 14.64 | N32: PCFX | O32: =SUMIF($C$2:$C$16599,N32,$K$2:$K$16599) -> 0.03
A33: 32 | B33: Call of Duty: Black Ops | C33: X360 | D33: 2010 | E33: Shooter | F33: Activision | G33: 9.67 | H33: 3.73 | I33: 0.11 | J33: 1.13 | K33: 14.64
A34: 33 | B34: Pokemon X/Pokemon Y | C34: 3DS | D34: 2013 | E34: Role-Playing | F34: Nintendo | G34: 5.17 | H34: 4.05 | I34: 4.34 | J34: 0.79 | K34: 14.35
A35: 34 | B35: Call of Duty: Black Ops 3 | C35: PS4 | D35: 2015 | E35: Shooter | F35: Activision | G35: 5.77 | H35: 5.81 | I35: 0.35 | J35: 2.31 | K35: 14.24
A36: 35 | B36: Call of Duty: Black Ops II | C36: PS3 | D36: 2012 | E36: Shooter | F36: Activision | G36: 4.99 | H36: 5.88 | I36: 0.65 | J36: 2.52 | K36: 14.03
A37: 36 | B37: Call of Duty: Black Ops II | C37: X360 | D37: 2012 | E37: Shooter | F37: Activision | G37: 8.25 | H37: 4.3 | I37: 0.07 | J37: 1.12 | K37: 13.73
A38: 37 | B38: Call of Duty: Modern Warfare 2 | C38: X360 | D38: 2009 | E38: Shooter | F38: Activision | G38: 8.52 | H38: 3.63 | I38: 0.08 | J38: 1.29 | K38: 13.51
A39: 38 | B39: Call of Duty: Modern Warfare 3 | C39: PS3 | D39: 2011 | E39: Shooter | F39: Activision | G39: 5.54 | H39: 5.82 | I39: 0.49 | J39: 1.62 | K39: 13.46
A40: 39 | B40: Grand Theft Auto III | C40: PS2 | D40: 2001 | E40: Action | F40: Take-Two Interactive | G40: 6.99 | H40: 4.51 | I40: 0.3 | J40: 1.3 | K40: 13.1
A41: 40 | B41: Super Smash Bros. Brawl | C41: Wii | D41: 2008 | E41: Fighting | F41: Nintendo | G41: 6.75 | H41: 2.61 | I41: 2.66 | J41: 1.02 | K41: 13.04
A42: 41 | B42: Call of Duty: Black Ops | C42: PS3 | D42: 2010 | E42: Shooter | F42: Activision | G42: 5.98 | H42: 4.44 | I42: 0.48 | J42: 1.83 | K42: 12.73
A43: 42 | B43: Animal Crossing: Wild World | C43: DS | D43: 2005 | E43: Simulation | F43: Nintendo | G43: 2.55 | H43: 3.52 | I43: 5.33 | J43: 0.88 | K43: 12.27
A44: 43 | B44: Mario Kart 7 | C44: 3DS | D44: 2011 | E44: Racing | F44: Nintendo | G44: 4.74 | H44: 3.91 | I44: 2.67 | J44: 0.89 | K44: 12.21
... A90: 89 | B90: PokÃ©mon Platinum Version | C90: DS | D90: 2008 | E90: Role-Playing | F90: Nintendo | G90: 2.82 | H90: 1.78 | I90: 2.69 | J90: 0.55 | K90: 7.84
A91: 90 | B91: Pac-Man | C91: 2600 | D91: 1982 | E91: Puzzle | F91: Atari | G91: 7.28 | H91: 0.45 | I91: 0 | J91: 0.08 | K91: 7.81
A92: 91 | B92: Grand Theft Auto: Liberty City Stories | C92: PSP | D92: 2005 | E92: Action | F92: Take-Two Interactive | G92: 2.9 | H92: 2.83 | I92: 0.24 | J92: 1.75 | K92: 7.72
A93: 92 | B93: Super Mario Galaxy 2 | C93: Wii | D93: 2010 | E93: Platform | F93: Nintendo | G93: 3.66 | H93: 2.42 | I93: 0.98 | J93: 0.64 | K93: 7.69
A94: 93 | B94: Star Wars Battlefront (2015) | C94: PS4 | D94: 2015 | E94: Shooter | F94: Electronic Arts | G94: 2.93 | H94: 3.29 | I94: 0.22 | J94: 1.23 | K94: 7.67
A95: 94 | B95: Call of Duty: Advanced Warfare | C95: PS4 | D95: 2014 | E95: Shooter | F95: Activision | G95: 2.8 | H95: 3.3 | I95: 0.14 | J95: 1.37 | K95: 7.6
A96: 95 | B96: The Legend of Zelda: Ocarina of Time | C96: N64 | D96: 1998 | E96: Action | F96: Nintendo | G96: 4.1 | H96: 1.89 | I96: 1.45 | J96: 0.16 | K96: 7.6
A97: 96 | B97: Crash Bandicoot 2: Cortex Strikes Back | C97: PS | D97: 1997 | E97: Platform | F97: Sony Computer Entertainment | G97: 3.78 | H97: 2.17 | I97: 1.31 | J97: 0.31 | K97: 7.58
A98: 97 | B98: Super Mario Bros. 2 | C98: NES | D98: 1988 | E98: Platform | F98: Nintendo | G98: 5.39 | H98: 1.18 | I98: 0.7 | J98: 0.19 | K98: 7.46
A99: 98 | B99: Super Smash Bros. for Wii U and 3DS | C99: 3DS | D99: 2014 | E99: Fighting | F99: Nintendo | G99: 3.24 | H99: 1.35 | I99: 2.42 | J99: 0.43 | K99: 7.45
A100: 99 | B100: Call of Duty: World at War | C100: X360 | D100: 2008 | E100: Shooter | F100: Activision | G100: 4.79 | H100: 1.9 | I100: 0 | J100: 0.69 | K100: 7.37
A101: 100 | B101: Battlefield 3 | C101: X360 | D101: 2011 | E101: Shooter | F101: Electronic Arts | G101: 4.46 | H101: 2.13 | I101: 0.06 | J101: 0.69 | K101: 7.34
A102: 101 | B102: The Legend of Zelda: Twilight Princess | C102: Wii | D102: 2006 | E102: Action | F102: Nintendo | G102: 3.83 | H102: 2.19 | I102: 0.6 | J102: 0.7 | K102: 7.31
A103: 102 | B103: Call of Duty: Black Ops 3 | C103: XOne | D103: 2015 | E103: Shooter | F103: Activision | G103: 4.52 | H103: 2.09 | I103: 0.01 | J103: 0.67 | K103: 7.3
... A180: 179 | B180: Tomb Raider II | C180: PS | D180: 1997 | E180: Action | F180: Eidos Interactive | G180: 2.3 | H180: 2.46 | I180: 0.2 | J180: 0.28 | K180: 5.24
A181: 180 | B181: Madden NFL 2004 | C181: PS2 | D181: N/A | E181: Sports | F181: Electronic Arts | G181: 4.26 | H181: 0.26 | I181: 0.01 | J181: 0.71 | K181: 5.23
A182: 181 | B182: Dragon Quest VIII: Journey of the Cursed King | C182: PS2 | D182: 2004 | E182: Role-Playing | F182: Square Enix | G182: 0.65 | H182: 0.75 | I182: 3.61 | J182: 0.2 | K182: 5.21
A183: 182 | B183: Diablo III | C183: PC | D183: 2012 | E183: Role-Playing | F183: Activision | G183: 2.43 | H183: 2.15 | I183: 0 | J183: 0.62 | K183: 5.2
A184: 183 | B184: Super Mario Bros. 3 | C184: GBA | D184: 2003 | E184: Platform | F184: Nintendo | G184: 2.93 | H184: 1.25 | I184: 0.83 | J184: 0.2 | K184: 5.2
A185: 184 | B185: New Super Mario Bros. U | C185: WiiU | D185: 2012 | E185: Platform | F185: Nintendo | G185: 2.32 | H185: 1.3 | I185: 1.27 | J185: 0.31 | K185: 5.19
A186: 185 | B186: Super Mario Land 3: Wario Land | C186: GB | D186: 1994 | E186: Platform | F186: Nintendo | G186: 2.49 | H186: 0.98 | I186: 1.57 | J186: 0.15 | K186: 5.19
A187: 186 | B187: FIFA Soccer 13 | C187: X360 | D187: 2012 | E187: Action | F187: Electronic Arts | G187: 1.08 | H187: 3.48 | I187: 0.03 | J187: 0.58 | K187: 5.18
A188: 187 | B188: The Legend of Zelda: Phantom Hourglass | C188: DS | D188: 2007 | E188: Action | F188: Nintendo | G188: 1.9 | H188: 1.83 | I188: 0.95 | J188: 0.49 | K188: 5.17
A189: 188 | B189: Donkey Kong Country 2: Diddy's Kong Quest | C189: SNES | D189: 1995 | E189: Platform | F189: Nintendo | G189: 2.1 | H189: 0.74 | I189: 2.2 | J189: 0.11 | K189: 5.15
A190: 189 | B190: Tomodachi Life | C190: 3DS | D190: 2013 | E190: Simulation | F190: Nintendo | G190: 0.96 | H190: 2.02 | I190: 1.89 | J190: 0.28 | K190: 5.15
A191: 190 | B191: Mario & Sonic at the Olympic Games | C191: DS | D191: 2008 | E191: Sports | F191: Sega | G191: 1.64 | H191: 2.48 | I191: 0.44 | J191: 0.58 | K191: 5.14
A192: 191 | B192: Medal of Honor: Rising Sun | C192: PS2 | D192: 2003 | E192: Shooter | F192: Electronic Arts | G192: 1.98 | H192: 2.23 | I192: 0.13 | J192: 0.8 | K192: 5.13
A193: 192 | B193: Kirby's Dream Land | C193: GB | D193: 1992 | E193: Platform | F193: Nintendo | G193: 2.71 | H193: 0.61 | I193: 1.7 | J193: 0.11 | K193: 5.13
... A240: 239 | B240: Madden NFL 2005 | C240: PS2 | D240: 2004 | E240: Sports | F240: Electronic Arts | G240: 4.18 | H240: 0.26 | I240: 0.01 | J240: 0.08 | K240: 4.53
A241: 240 | B241: Pitfall! | C241: 2600 | D241: 1981 | E241: Platform | F241: Activision | G241: 4.21 | H241: 0.24 | I241: 0 | J241: 0.05 | K241: 4.5
A242: 241 | B242: Madden NFL 07 | C242: PS2 | D242: 2006 | E242: Sports | F242: Electronic Arts | G242: 3.63 | H242: 0.24 | I242: 0.01 | J242: 0.61 | K242: 4.49
A243: 242 | B243: Spider-Man: The Movie | C243: PS2 | D243: 2002 | E243: Action | F243: Activision | G243: 2.71 | H243: 1.51 | I243: 0.03 | J243: 0.23 | K243: 4.48
A244: 243 | B244: Dragon Quest VII: Warriors of Eden | C244: PS | D244: 2000 | E244: Role-Playing | F244: Enix Corporation | G244: 0.2 | H244: 0.14 | I244: 4.1 | J244: 0.02 | K244: 4.47
A245: 244 | B245: Uncharted: The Nathan Drake Collection | C245: PS4 | D245: 2015 | E245: Action | F245: Sony Computer Entertainment | G245: 1.96 | H245: 1.69 | I245: 0.08 | J245: 0.74 | K245: 4.47
A246: 245 | B246: Call of Duty: Advanced Warfare | C246: PS3 | D246: 2014 | E246: Shooter | F246: Activision | G246: 1.54 | H246: 1.94 | I246: 0.19 | J246: 0.77 | K246: 4.45
A247: 246 | B247: God of War | C247: PS2 | D247: 2005 | E247: Action | F247: Sony Computer Entertainment | G247: 2.71 | H247: 1.29 | I247: 0.02 | J247: 0.43 | K247: 4.45
A248: 247 | B248: Nintendo Land | C248: WiiU | D248: 2012 | E248: Misc | F248: Nintendo | G248: 2.55 | H248: 1.11 | I248: 0.46 | J248: 0.33 | K248: 4.44
A249: 248 | B249: Michael Jackson: The Experience | C249: Wii | D249: 2010 | E249: Misc | F249: Ubisoft | G249: 2.67 | H249: 1.35 | I249: 0.01 | J249: 0.39 | K249: 4.42
A250: 249 | B250: Tony Hawk's Pro Skater 3 | C250: PS2 | D250: 2001 | E250: Sports | F250: Activision | G250: 2.66 | H250: 1.29 | I250: 0.01 | J250: 0.46 | K250: 4.41
A251: 250 | B251: Winning Eleven: Pro Evolution Soccer 2007 | C251: PS2 | D251: 2006 | E251: Sports | F251: Konami Digital Entertainment | G251: 0.1 | H251: 2.39 | I251: 1.05 | J251: 0.86 | K251: 4.39
A252: 251 | B252: The Elder Scrolls IV: Oblivion | C252: X360 | D252: 2006 | E252: Role-Playing | F252: Take-Two Interactive | G252: 2.82 | H252: 1.05 | I252: 0.13 | J252: 0.4 | K252: 4.39
A253: 252 | B253: Zelda II: The Adventure of Link | C253: NES | D253: 1987 | E253: Adventure | F253: Nintendo | G253: 2.19 | H253: 0.5 | I253: 1.61 | J253: 0.08 | K253: 4.38
... A259: 258 | B259: Call of Duty: Advanced Warfare | C259: X360 | D259: 2014 | E259: Shooter | F259: Activision | G259: 2.75 | H259: 1.18 | I259: 0 | J259: 0.37 | K259: 4.31
A260: 259 | B260: Asteroids | C260: 2600 | D260: 1980 | E260: Shooter | F260: Atari | G260: 4 | H260: 0.26 | I260: 0 | J260: 0.05 | K260: 4.31
A261: 260 | B261: Fable II | C261: X360 | D261: 2008 | E261: Role-Playing | F261: Microsoft Game Studios | G261: 2.51 | H261: 1.27 | I261: 0.11 | J261: 0.41 | K261: 4.31
A262: 261 | B262: Halo 5: Guardians | C262: XOne | D262: 2015 | E262: Shooter | F262: Microsoft Game Studios | G262: 2.64 | H262: 1.2 | I262: 0.03 | J262: 0.39 | K262: 4.26
A263: 262 | B263: Super Mario 3D World | C263: WiiU | D263: 2013 | E263: Platform | F263: Nintendo | G263: 2.11 | H263: 1.11 | I263: 0.72 | J263: 0.3 | K263: 4.25
A264: 263 | B264: Batman: Arkham Asylum | C264: PS3 | D264: 2009 | E264: Action | F264: Eidos Interactive | G264: 2.23 | H264: 1.34 | I264: 0.07 | J264: 0.61 | K264: 4.25
A265: 264 | B265: Assassin's Creed: Revelations | C265: PS3 | D265: 2011 | E265: Action | F265: Ubisoft | G265: 1.41 | H265: 2.02 | I265: 0.1 | J265: 0.72 | K265: 4.24
A266: 265 | B266: Namco Museum | C266: GBA | D266: 2001 | E266: Misc | F266: Namco Bandai Games | G266: 3 | H266: 1.11 | I266: 0.05 | J266: 0.07 | K266: 4.24
A267: 266 | B267: Metal Gear Solid 3: Snake Eater | C267: PS2 | D267: 2004 | E267: Action | F267: Konami Digital Entertainment | G267: 1.46 | H267: 0 | I267: 0.83 | J267: 1.93 | K267: 4.23
A268: 267 | B268: Daxter | C268: PSP | D268: 2006 | E268: Platform | F268: Sony Computer Entertainment | G268: 2.45 | H268: 1.02 | I268: 0 | J268: 0.75 | K268: 4.22
A269: 268 | B269: Warcraft II: Tides of Darkness | C269: PC | D269: 1995 | E269: Strategy | F269: Activision | G269: 1.7 | H269: 2.27 | I269: 0 | J269: 0.23 | K269: 4.21
A270: 269 | B270: The Legend of Zelda: Ocarina of Time | C270: 3DS | D270: 2011 | E270: Action | F270: Nintendo | G270: 2.03 | H270: 1.27 | I270: 0.62 | J270: 0.3 | K270: 4.21
A271: 270 | B271: FIFA Soccer 06 | C271: PS2 | D271: 2005 | E271: Sports | F271: Electronic Arts | G271: 0.78 | H271: 2.55 | I271: 0.04 | J271: 0.84 | K271: 4.21
A272: 271 | B272: EyeToy Play | C272: PS2 | D272: 2003 | E272: Misc | F272: Sony Computer Entertainment | G272: 0.88 | H272: 2.3 | I272: 0.2 | J272: 0.83 | K272: 4.2
... A378: 377 | B378: Clubhouse Games | C378: DS | D378: 2006 | E378: Misc | F378: Nintendo | G378: 0.59 | H378: 1.83 | I378: 0.73 | J378: 0.35 | K378: 3.5
A379: 378 | B379: FIFA Soccer 2004 | C379: PS2 | D379: N/A | E379: Sports | F379: Electronic Arts | G379: 0.59 | H379: 2.36 | I379: 0.04 | J379: 0.51 | K379: 3.49
A380: 379 | B380: Star Wars Battlefront (2015) | C380: XOne | D380: 2015 | E380: Shooter | F380: Electronic Arts | G380: 1.94 | H380: 1.22 | I380: 0.02 | J380: 0.31 | K380: 3.49
A381: 380 | B381: Battlefield: Bad Company 2 | C381: X360 | D381: 2010 | E381: Shooter | F381: Electronic Arts | G381: 2.09 | H381: 1.02 | I381: 0.04 | J381: 0.32 | K381: 3.48
A382: 381 | B382: Guitar Hero: On Tour | C382: DS | D382: 2008 | E382: Misc | F382: Activision | G382: 2.11 | H382: 1.01 | I382: 0.01 | J382: 0.35 | K382: 3.48
...

Sheet Sales by X
B2: Platform | C2: Total Global Copies Sold | E2: Year | F2: Total Global Copies Sold | H2: Genre | I2: Total Global Copies Sold | K2: Publisher | L2: Total Global Copies Sold
B3: PS2 | C3: 1255.64 | E3: 1980 | F3: =SUMIF(vgsales!$D$2:$D$16599,'Sales by X'!E3,vgsales!$K$2:$K$16599) -> 11.38 | H3: Sports | I3: =SUMIF(vgsales!$E$2:$E$16599,'Sales by X'!H3,vgsales!$K$2:$K$16599) -> 1330.93 | K3: Nintendo | L3: =SUMIF(vgsales!$F$2:$F$16599,'Sales by X'!K3,vgsales!$K$2:$K$16599) -> 1786.56
B4: X360 | C4: 979.96 | E4: 1981 | F4: =SUMIF(vgsales!$D$2:$D$16599,'Sales by X'!E4,vgsales!$K$2:$K$16599) -> 35.77 | H4: Platform | I4: =SUMIF(vgsales!$E$2:$E$16599,'Sales by X'!H4,vgsales!$K$2:$K$16599) -> 831.37 | K4: Microsoft Game Studios | L4: =SUMIF(vgsales!$F$2:$F$16599,'Sales by X'!K4,vgsales!$K$2:$K$16599) -> 245.79
B5: PS3 | C5: 957.84 | E5: 1982 | F5: =SUMIF(vgsales!$D$2:$D$16599,'Sales by X'!E5,vgsales!$K$2:$K$16599) -> 28.86 | H5: Racing | I5: =SUMIF(vgsales!$E$2:$E$16599,'Sales by X'!H5,vgsales!$K$2:$K$16599) -> 732.04 | K5: Take-Two Interactive | L5: =SUMIF(vgsales!$F$2:$F$16599,'Sales by X'!K5,vgsales!$K$2:$K$16599) -> 399.54
B6: Wii | C6: 926.71 | E6: 1983 | F6: =SUMIF(vgsales!$D$2:$D$16599,'Sales by X'!E6,vgsales!$K$2:$K$16599) -> 16.79 | H6: Sports | I6: =SUMIF(vgsales!$E$2:$E$16599,'Sales by X'!H6,vgsales!$K$2:$K$16599) -> 1330.93 | K6: Sony Computer Entertainment | L6: =SUMIF(vgsales!$F$2:$F$16599,'Sales by X'!K6,vgsales!$K$2:$K$16599) -> 607.5
B7: Wii | C7: 926.71 | E7: 1984 | F7: =SUMIF(vgsales!$D$2:$D$16599,'Sales by X'!E7,vgsales!$K$2:$K$16599) -> 50.36 | H7: Role-Playing | I7: =SUMIF(vgsales!$E$2:$E$16599,'Sales by X'!H7,vgsales!$K$2:$K$16599) -> 927.37 | K7: Activision | L7: =SUMIF(vgsales!$F$2:$F$16599,'Sales by X'!K7,vgsales!$K$2:$K$16599) -> 727.46
B8: DS | C8: 822.49 | E8: 1985 | F8: =SUMIF(vgsales!$D$2:$D$16599,'Sales by X'!E8,vgsales!$K$2:$K$16599) -> 53.94 | H8: Puzzle | I8: =SUMIF(vgsales!$E$2:$E$16599,'Sales by X'!H8,vgsales!$K$2:$K$16599) -> 244.95 | K8: Ubisoft | L8: =SUMIF(vgsales!$F$2:$F$16599,'Sales by X'!K8,vgsales!$K$2:$K$16599) -> 474.72
B9: PS | C9: 730.66 | E9: 1986 | F9: =SUMIF(vgsales!$D$2:$D$16599,'Sales by X'!E9,vgsales!$K$2:$K$16599) -> 37.07 | H9: Misc | I9: =SUMIF(vgsales!$E$2:$E$16599,'Sales by X'!H9,vgsales!$K$2:$K$16599) -> 809.96 | K9: Bethesda Softworks | L9: =SUMIF(vgsales!$F$2:$F$16599,'Sales by X'!K9,vgsales!$K$2:$K$16599) -> 82.14
B10: GBA | C10: 318.5 | E10: 1987 | F10: =SUMIF(vgsales!$D$2:$D$16599,'Sales by X'!E10,vgsales!$K$2:$K$16599) -> 21.74 | H10: Shooter | I10: =SUMIF(vgsales!$E$2:$E$16599,'Sales by X'!H10,vgsales!$K$2:$K$16599) -> 1037.37 | K10: Electronic Arts | L10: =SUMIF(vgsales!$F$2:$F$16599,'Sales by X'!K10,vgsales!$K$2:$K$16599) -> 1110.32
B11: PSP | C11: 296.28 | E11: 1988 | F11: =SUMIF(vgsales!$D$2:$D$16599,'Sales by X'!E11,vgsales!$K$2:$K$16599) -> 47.22 | H11: Simulation | I11: =SUMIF(vgsales!$E$2:$E$16599,'Sales by X'!H11,vgsales!$K$2:$K$16599) -> 392.2 | K11: Sega | L11: =SUMIF(vgsales!$F$2:$F$16599,'Sales by X'!K11,vgsales!$K$2:$K$16599) -> 272.99
B12: PS4 | C12: 278.1 | E12: 1989 | F12: =SUMIF(vgsales!$D$2:$D$16599,'Sales by X'!E12,vgsales!$K$2:$K$16599) -> 73.45 | H12: Action | I12: =SUMIF(vgsales!$E$2:$E$16599,'Sales by X'!H12,vgsales!$K$2:$K$16599) -> 1751.18 | K12: SquareSoft | L12: =SUMIF(vgsales!$F$2:$F$16599,'Sales by X'!K12,vgsales!$K$2:$K$16599) -> 57.65
B13: PC | C13: 258.82 | E13: 1990 | F13: =SUMIF(vgsales!$D$2:$D$16599,'Sales by X'!E13,vgsales!$K$2:$K$16599) -> 49.39 | H13: Fighting | I13: =SUMIF(vgsales!$E$2:$E$16599,'Sales by X'!H13,vgsales!$K$2:$K$16599) -> 448.91 | K13: Atari | L13: =SUMIF(vgsales!$F$2:$F$16599,'Sales by X'!K13,vgsales!$K$2:$K$16599) -> 157.22
B14: XB | C14: 258.26 | E14: 1991 | F14: =SUMIF(vgsales!$D$2:$D$16599,'Sales by X'!E14,vgsales!$K$2:$K$16599) -> 32.23 | H14: Adventure | I14: =SUMIF(vgsales!$E$2:$E$16599,'Sales by X'!H14,vgsales!$K$2:$K$16599) -> 239.04 | K14: 505 Games | L14: =SUMIF(vgsales!$F$2:$F$16599,'Sales by X'!K14,vgsales!$K$2:$K$16599) -> 55.91
B15: GB | C15: 255.45 | E15: 1992 | F15: =SUMIF(vgsales!$D$2:$D$16599,'Sales by X'!E15,vgsales!$K$2:$K$16599) -> 76.16 | H15: Strategy | I15: =SUMIF(vgsales!$E$2:$E$16599,'Sales by X'!H15,vgsales!$K$2:$K$16599) -> 175.12 | K15: Capcom | L15: =SUMIF(vgsales!$F$2:$F$16599,'Sales by X'!K15,vgsales!$K$2:$K$16599) -> 200.89
B16: NES | C16: 251.07 | E16: 1993 | F16: =SUMIF(vgsales!$D$2:$D$16599,'Sales by X'!E16,vgsales!$K$2:$K$16599) -> 45.98 | K16: GT Interactive | L16: =SUMIF(vgsales!$F$2:$F$16599,'Sales by X'!K16,vgsales!$K$2:$K$16599) -> 25.23
B17: 3DS | C17: 247.46 | E17: 1994 | F17: =SUMIF(vgsales!$D$2:$D$16599,'Sales by X'!E17,vgsales!$K$2:$K$16599) -> 79.17 | K17: Konami Digital Entertainment | L17: =SUMIF(vgsales!$F$2:$F$16599,'Sales by X'!K17,vgsales!$K$2:$K$16599) -> 283.64
B18: N64 | C18: 218.88 | E18: 1995 | F18: =SUMIF(vgsales!$D$2:$D$16599,'Sales by X'!E18,vgsales!$K$2:$K$16599) -> 88.11 | K18: Sony Computer Entertainment Europe | L18: =SUMIF(vgsales!$F$2:$F$16599,'Sales by X'!K18,vgsales!$K$2:$K$16599) -> 23.89
B19: SNES | C19: 200.05 | E19: 1996 | F19: =SUMIF(vgsales!$D$2:$D$16599,'Sales by X'!E19,vgsales!$K$2:$K$16599) -> 199.15 | K19: Square Enix | L19: =SUMIF(vgsales!$F$2:$F$16599,'Sales by X'!K19,vgsales!$K$2:$K$16599) -> 145.18
B20: GC | C20: 199.36 | E20: 1997 | F20: =SUMIF(vgsales!$D$2:$D$16599,'Sales by X'!E20,vgsales!$K$2:$K$16599) -> 200.98 | K20: LucasArts | L20: =SUMIF(vgsales!$F$2:$F$16599,'Sales by X'!K20,vgsales!$K$2:$K$16599) -> 87.34
B21: XOne | C21: 141.06 | E21: 1998 | F21: =SUMIF(vgsales!$D$2:$D$16599,'Sales by X'!E21,vgsales!$K$2:$K$16599) -> 256.47 | K21: Virgin Interactive | L21: =SUMIF(vgsales!$F$2:$F$16599,'Sales by X'!K21,vgsales!$K$2:$K$16599) -> 43.87
B22: 2600 | C22: 97.08 | E22: 1999 | F22: =SUMIF(vgsales!$D$2:$D$16599,'Sales by X'!E22,vgsales!$K$2:$K$16599) -> 251.27 | K22: Warner Bros. Interactive Entertainment | L22: =SUMIF(vgsales!$F$2:$F$16599,'Sales by X'!K22,vgsales!$K$2:$K$16599) -> 153.89
B23: WiiU | C23: 81.86 | E23: 2000 | F23: =SUMIF(vgsales!$D$2:$D$16599,'Sales by X'!E23,vgsales!$K$2:$K$16599) -> 201.56 | K23: Universal Interactive | L23: =SUMIF(vgsales!$F$2:$F$16599,'Sales by X'!K23,vgsales!$K$2:$K$16599) -> 17.77
B24: PSV | C24: 61.93 | E24: 2001 | F24: =SUMIF(vgsales!$D$2:$D$16599,'Sales by X'!E24,vgsales!$K$2:$K$16599) -> 331.47 | K24: Eidos Interactive | L24: =SUMIF(vgsales!$F$2:$F$16599,'Sales by X'!K24,vgsales!$K$2:$K$16599) -> 98.98
B25: SAT | C25: 33.59 | E25: 2002 | F25: =SUMIF(vgsales!$D$2:$D$16599,'Sales by X'!E25,vgsales!$K$2:$K$16599) -> 395.52 | K25: RedOctane | L25: =SUMIF(vgsales!$F$2:$F$16599,'Sales by X'!K25,vgsales!$K$2:$K$16599) -> 8.68
B26: GEN | C26: 28.36 | E26: 2003 | F26: =SUMIF(vgsales!$D$2:$D$16599,'Sales by X'!E26,vgsales!$K$2:$K$16599) -> 357.85 | K26: Vivendi Games | L26: =SUMIF(vgsales!$F$2:$F$16599,'Sales by X'!K26,vgsales!$K$2:$K$16599) -> 58.21
B27: DC | C27: 15.97 | E27: 2004 | F27: =SUMIF(vgsales!$D$2:$D$16599,'Sales by X'!E27,vgsales!$K$2:$K$16599) -> 419.31 | K27: Enix Corporation | L27: =SUMIF(vgsales!$F$2:$F$16599,'Sales by X'!K27,vgsales!$K$2:$K$16599) -> 33.74
B28: SCD | C28: 1.87 | E28: 2005 | F28: =SUMIF(vgsales!$D$2:$D$16599,'Sales by X'!E28,vgsales!$K$2:$K$16599) -> 459.94 | K28: Namco Bandai Games | L28: =SUMIF(vgsales!$F$2:$F$16599,'Sales by X'!K28,vgsales!$K$2:$K$16599) -> 254.09
B29: NG | C29: 1.44 | E29: 2006 | F29: =SUMIF(vgsales!$D$2:$D$16599,'Sales by X'!E29,vgsales!$K$2:$K$16599) -> 521.04 | K29: Palcom | L29: =SUMIF(vgsales!$F$2:$F$16599,'Sales by X'!K29,vgsales!$K$2:$K$16599) -> 4.17
B30: WS | C30: 1.42 | E30: 2007 | F30: =SUMIF(vgsales!$D$2:$D$16599,'Sales by X'!E30,vgsales!$K$2:$K$16599) -> 611.13 | K30: Hasbro Interactive | L30: =SUMIF(vgsales!$F$2:$F$16599,'Sales by X'!K30,vgsales!$K$2:$K$16599) -> 15.22
B31: TG16 | C31: 0.16 | E31: 2008 | F31: =SUMIF(vgsales!$D$2:$D$16599,'Sales by X'!E31,vgsales!$K$2:$K$16599) -> 678.9 | K31: THQ | L31: =SUMIF(vgsales!$F$2:$F$16599,'Sales by X'!K31,vgsales!$K$2:$K$16599) -> 340.77
B32: 3DO | C32: 0.1 | E32: 2009 | F32: =SUMIF(vgsales!$D$2:$D$16599,'Sales by X'!E32,vgsales!$K$2:$K$16599) -> 667.3 | K32: Fox Interactive | L32: =SUMIF(vgsales!$F$2:$F$16599,'Sales by X'!K32,vgsales!$K$2:$K$16599) -> 7.39
B33: GG | C33: 0.04 | E33: 2010 | F33: =SUMIF(vgsales!$D$2:$D$16599,'Sales by X'!E33,vgsales!$K$2:$K$16599) -> 600.45 | K33: Acclaim Entertainment | L33: =SUMIF(vgsales!$F$2:$F$16599,'Sales by X'!K33,vgsales!$K$2:$K$16599) -> 64.14
B34: PCFX | C34: 0.03 | E34: 2011 | F34: =SUMIF(vgsales!$D$2:$D$16599,'Sales by X'!E34,vgsales!$K$2:$K$16599) -> 515.99 | K34: MTV Games | L34: =SUMIF(vgsales!$F$2:$F$16599,'Sales by X'!K34,vgsales!$K$2:$K$16599) -> 20.97
E35: 2012 | F35: =SUMIF(vgsales!$D$2:$D$16599,'Sales by X'!E35,vgsales!$K$2:$K$16599) -> 363.54 | K35: Disney Interactive Studios | L35: =SUMIF(vgsales!$F$2:$F$16599,'Sales by X'!K35,vgsales!$K$2:$K$16599) -> 119.96
E36: 2013 | F36: =SUMIF(vgsales!$D$2:$D$16599,'Sales by X'!E36,vgsales!$K$2:$K$16599) -> 368.11 | K36: N/A | L36: =SUMIF(vgsales!$F$2:$F$16599,'Sales by X'!K36,vgsales!$K$2:$K$16599) -> 14.88
E37: 2014 | F37: =SUMIF(vgsales!$D$2:$D$16599,'Sales by X'!E37,vgsales!$K$2:$K$16599) -> 337.05 | K37: Majesco Entertainment | L37: =SUMIF(vgsales!$F$2:$F$16599,'Sales by X'!K37,vgsales!$K$2:$K$16599) -> 16.08
E38: 2015 | F38: =SUMIF(vgsales!$D$2:$D$16599,'Sales by X'!E38,vgsales!$K$2:$K$16599) -> 264.44 | K38: Codemasters | L38: =SUMIF(vgsales!$F$2:$F$16599,'Sales by X'!K38,vgsales!$K$2:$K$16599) -> 47.87
E39: 2016 | F39: =SUMIF(vgsales!$D$2:$D$16599,'Sales by X'!E39,vgsales!$K$2:$K$16599) -> 70.93 | K39: Red Orb | L39: =SUMIF(vgsales!$F$2:$F$16599,'Sales by X'!K39,vgsales!$K$2:$K$16599) -> 5.24
K40: Level 5 | L40: =SUMIF(vgsales!$F$2:$F$16599,'Sales by X'!K40,vgsales!$K$2:$K$16599) -> 12.17
K41: Arena Entertainment | L41: =SUMIF(vgsales!$F$2:$F$16599,'Sales by X'!K41,vgsales!$K$2:$K$16599) -> 4.72
K42: Midway Games | L42: =SUMIF(vgsales!$F$2:$F$16599,'Sales by X'!K42,vgsales!$K$2:$K$16599) -> 69.85
K43: JVC | L43: =SUMIF(vgsales!$F$2:$F$16599,'Sales by X'!K43,vgsales!$K$2:$K$16599) -> 2.8
K44: Deep Silver | L44: =SUMIF(vgsales!$F$2:$F$16599,'Sales by X'!K44,vgsales!$K$2:$K$16599) -> 25.67
K45: 989 Studios | L45: =SUMIF(vgsales!$F$2:$F$16599,'Sales by X'!K45,vgsales!$K$2:$K$16599) -> 13.32
K46: NCSoft | L46: =SUMIF(vgsales!$F$2:$F$16599,'Sales by X'!K46,vgsales!$K$2:$K$16599) -> 2.59
K47: UEP Systems | L47: =SUMIF(vgsales!$F$2:$F$16599,'Sales by X'!K47,vgsales!$K$2:$K$16599) -> 2.25
K48: Parker Bros. | L48: =SUMIF(vgsales!$F$2:$F$16599,'Sales by X'!K48,vgsales!$K$2:$K$16599) -> 4.97
K49: Maxis | L49: =SUMIF(vgsales!$F$2:$F$16599,'Sales by X'!K49,vgsales!$K$2:$K$16599) -> 3.39
K50: Imagic | L50: =SUMIF(vgsales!$F$2:$F$16599,'Sales by X'!K50,vgsales!$K$2:$K$16599) -> 4.82
K51: Tecmo Koei | L51: =SUMIF(vgsales!$F$2:$F$16599,'Sales by X'!K51,vgsales!$K$2:$K$16599) -> 53.55
... K581: UIG Entertainment | L581: =SUMIF(vgsales!$F$2:$F$16599,'Sales by X'!K581,vgsales!$K$2:$K$16599) -> 0.01
